Workbook

Sheet Read me
A1: The Reimbursement Playbook — working template (Hubricon)
A3: What this is: one sheet per Amazon report, a Claims sheet that dates and values every claim, and a filing log.
A4: Every window and approval assumption on the Windows sheet is the same constant Hubricon's engine runs; change a cell there and every claim recalculates.
A6: How to use it:
A7: 1. Windows: set 'As of' to today (it is =TODAY() by default).
A8: 2. COGS: paste your landed cost per SKU (unit cost + inbound freight + packaging). Claims are valued at landed cost; Amazon reimburses at manufacturing cost.
A9: 3. Ledger / Returns / Reimbursements / Refunds: paste the raw exports. The helper columns on the right classify each row.
A10: 4. Claims: one row per loss you are filing. Type, SKU, event date and units are yours; everything else is a formula.
A11: 5. Filing log: the case id, the date filed, what Amazon paid, and whether it paid in cash or in kind.
A13: The rows already here are demo data from a fictional catalogue (Tarnhollow). Delete them before you paste your own.
A14: Inbound-shipment shortages are not in this playbook: they need the shipment reconciliation export.
A16: Free training and the written playbook: https://www.hubricon.com/learn/reimbursement-playbook

Sheet Windows
A1: Setting | B1: Value | C1: What it means | D1: Source
A2: as_of | B2: =TODAY() | C2: The date every claim is judged against; the demo rows were judged as of 2026-09-01 | D2: you
A3: warehouse_eligible_after_days | B3: 30 | C3: Days after a warehouse loss or damage before you may file | D3: hubricon_engine.models.recovery
A4: warehouse_deadline_days | B4: 60 | C4: Days after a warehouse loss or damage until the window shuts | D4: hubricon_engine.models.recovery
A5: refund_min_age_days | B5: 45 | C5: A refund younger than this is not a claim yet | D5: hubricon_engine.models.recovery
A6: refund_eligible_after_days | B6: 60 | C6: Days after a refund before a no-return claim may be filed | D6: hubricon_engine.models.recovery
A7: refund_deadline_days | B7: 120 | C7: Days after a refund until the no-return window shuts | D7: hubricon_engine.models.recovery
A8: damaged_return_deadline_days | B8: 60 | C8: Days after a damaged return until the window shuts | D8: hubricon_engine.models.recovery
A9: expiring_within_days | B9: 14 | C9: A claim this close to its deadline is called expiring | D9: hubricon_engine.models.recovery
A10: found_match_window_days | B10: 45 | C10: A 'found' adjustment inside this many days offsets a loss | D10: hubricon_engine.models.recovery
A11: reimbursement_match_window_days | B11: 90 | C11: A paid reimbursement inside this many days offsets a loss | D11: hubricon_engine.models.recovery
A12: no_cost_value_fraction | B12: 0.5 | C12: Value fallback when no landed cost is on file, as a share of price | D12: hubricon_engine.models.recovery
A14: Claim type | B14: P(approve) | C14: What it means | D14: Source
A15: warehouse_lost | B15: 0.85 | C15: Stated assumption used for expected value; Amazon's own unreconciled counts approve more often | D15: hubricon_engine.models.recovery.P_APPROVE
A16: warehouse_damaged | B16: 0.85 | C16: Stated assumption used for expected value; Amazon's own unreconciled counts approve more often | D16: hubricon_engine.models.recovery.P_APPROVE
A17: carrier_damaged | B17: 0.7 | C17: Stated assumption used for expected value; Amazon's own unreconciled counts approve more often | D17: hubricon_engine.models.recovery.P_APPROVE
A18: transit_lost | B18: 0.7 | C18: Stated assumption used for expected value; Amazon's own unreconciled counts approve more often | D18: hubricon_engine.models.recovery.P_APPROVE
A19: refund_no_return | B19: 0.7 | C19: Stated assumption used for expected value; Amazon's own unreconciled counts approve more often | D19: hubricon_engine.models.recovery.P_APPROVE
A20: damaged_return | B20: 0.6 | C20: Stated assumption used for expected value; Amazon's own unreconciled counts approve more often | D20: hubricon_engine.models.recovery.P_APPROVE
A21: reimbursement_reversal | B21: 0.5 | C21: Stated assumption used for expected value; Amazon's own unreconciled counts approve more often | D21: hubricon_engine.models.recovery.P_APPROVE
A23: Claim type | B23: Eligible after (days) | C23: Deadline (days) | D23: Counted from
A24: warehouse_lost | B24: 30 | C24: 60 | D24: the adjustment date
A25: warehouse_damaged | B25: 30 | C25: 60 | D25: the adjustment date
A26: carrier_damaged | B26: 30 | C26: 60 | D26: the adjustment date
A27: transit_lost | B27: 30 | C27: 60 | D27: the adjustment date
A28: refund_no_return | B28: 60 | C28: 120 | D28: the refund date
A29: damaged_return | B29: 0 | C29: 60 | D29: the return date
A30: reimbursement_reversal | B30: 0 | C30: 60 | D30: the reversal date
A32: TYPE_TABLE_ROW | B32: 24

Sheet Reason codes
A1: Ledger reason | B1: Class | C1: Claimable?
A2: 5 | B2: found | C2: no
A3: 6 | B3: transit_lost | C3: yes
A4: D | B4: warehouse_damaged | C4: yes
A5: E | B5: customer_damaged | C5: no
A6: F | B6: found | C6: no
A7: H | B7: carrier_damaged | C7: yes
A8: K | B8: carrier_damaged | C8: yes
A9: M | B9: warehouse_lost | C9: yes
A10: N | B10: warehouse_lost | C10: yes
A11: O | B11: transfer | C11: no
A12: P | B12: disposed | C12: no
... A15: X | B15: transfer | C15: no

Sheet COGS
A1: sku | B1: product_name | C1: unit_cost_usd | D1: inbound_freight_per_unit_usd | E1: packaging_per_unit_usd | F1: other_cost_per_unit_usd | G1: landed_cost (formula)
A2: TH-APRWAX-21 | B2: Apron Waxed Canvas | C2: 9.6 | D2: 0.6 | E2: 0.4 | F2: 0 | G2: =SUM(C2:F2)
A3: TH-BAMCUT-05 | B3: Bamboo Cutting Board L | C3: 6.1 | D3: 1.4 | E3: 0.4 | F3: 0 | G3: =SUM(C3:F3)
A4: TH-BAMCUT-06 | B4: Bamboo Cutting Board M | C4: 4.2 | D4: 1 | E4: 0.3 | F4: 0 | G4: =SUM(C4:F4)
A5: TH-BREKNI-10 | B5: Bread Knife 10in | C5: 6.8 | D5: 0.7 | E5: 0.5 | F5: 0 | G5: =SUM(C5:F5)
A6: TH-CARSTE-04 | B6: Carbon Steel Wok | C6: 13.2 | D6: 2.3 | E6: 0.6 | F6: 0 | G6: =SUM(C6:F6)
A7: TH-CASIRO-01 | B7: Cast Iron Skillet 10in | C7: 9.4 | D7: 2.1 | E7: 0.6 | F7: 0 | G7: =SUM(C7:F7)
A8: TH-CASIRO-02 | B8: Cast Iron Skillet 12in | C8: 12.8 | D8: 2.6 | E8: 0.7 | F8: 0 | G8: =SUM(C8:F8)
A9: TH-CHEKNI-08 | B9: Chef Knife 8in | C9: 14.6 | D9: 1.1 | E9: 0.9 | F9: 0 | G9: =SUM(C9:F9)
A10: TH-COFCAN-19 | B10: Coffee Canister Airtight | C10: 5 | D10: 0.8 | E10: 0.4 | F10: 0 | G10: =SUM(C10:F10)
A11: TH-ENADUT-03 | B11: Enamel Dutch Oven 5qt | C11: 24.5 | D11: 4.2 | E11: 1.1 | F11: 0 | G11: =SUM(C11:F11)
A12: TH-FREPRE-17 | B12: French Press 34oz | C12: 7.1 | D12: 1.3 | E12: 0.6 | F12: 0 | G12: =SUM(C12:F12)
A13: TH-KITTOW-24 | B13: Kitchen Towels Linen 4pk | C13: 5.5 | D13: 0.5 | E13: 0.3 | F13: 0 | G13: =SUM(C13:F13)
... A25: TH-WALSER-07 | B25: Walnut Serving Tray | C25: 10.9 | D25: 1.7 | E25: 0.5 | F25: 0 | G25: =SUM(C25:F25)

Sheet Ledger
A1: Date | B1: FNSKU | C1: ASIN | D1: MSKU | E1: Title | F1: Event Type | G1: Reference ID | H1: Quantity | I1: Fulfillment Center | J1: Disposition | K1: Reason | L1: Country | M1: Reconciled Quantity | N1: Unreconciled Quantity | O1: Class (helper) | P1: Claimable (helper) | Q1: Units lost (helper)
A2: 2026-02-20 | B2: X0TH0012 | C2: B0TH012KX | D2: TH-STAMIX-12 | E2: Stainless Mixing Bowls 5pc | F2: Receipts | G2: FBA15TH77123 | H2: 495 | I2: MDW2 | J2: SELLABLE | L2: US | M2: 0 | N2: 0 | O2: =IFERROR(VLOOKUP(K2,'Reason codes'!$A$2:$B$40,2,FALSE),"") | P2: =IF(AND(ISNUMBER(SEARCH("adjust",F2)),OR(O2="warehouse_lost",O2="warehouse_damaged",O2="carrier_damaged",O2="transit_lost")),"yes","no") | Q2: =IF(P2="yes",IF(N2<>"",N2,MAX(0,-H2)),0)
A3: 2026-02-20 | B3: X0TH0020 | C3: B0TH020KX | D3: TH-TEAINF-20 | E3: Tea Infuser Mug | F3: Receipts | G3: FBA15TH77209 | H3: 570 | I3: PHX7 | J3: SELLABLE | L3: US | M3: 0 | N3: 0 | O3: =IFERROR(VLOOKUP(K3,'Reason codes'!$A$2:$B$40,2,FALSE),"") | P3: =IF(AND(ISNUMBER(SEARCH("adjust",F3)),OR(O3="warehouse_lost",O3="warehouse_damaged",O3="carrier_damaged",O3="transit_lost")),"yes","no") | Q3: =IF(P3="yes",IF(N3<>"",N3,MAX(0,-H3)),0)
A4: 2026-02-24 | B4: X0TH0005 | C4: B0TH005KX | D4: TH-BAMCUT-05 | E4: Bamboo Cutting Board L | F4: Receipts | G4: FBA15TH77047 | H4: 810 | I4: DFW6 | J4: SELLABLE | L4: US | M4: 0 | N4: 0 | O4: =IFERROR(VLOOKUP(K4,'Reason codes'!$A$2:$B$40,2,FALSE),"") | P4: =IF(AND(ISNUMBER(SEARCH("adjust",F4)),OR(O4="warehouse_lost",O4="warehouse_damaged",O4="carrier_damaged",O4="transit_lost")),"yes","no") | Q4: =IF(P4="yes",IF(N4<>"",N4,MAX(0,-H4)),0)
A5: 2026-03-05 | B5: X0TH0014 | C5: B0TH014KX | D5: TH-MEACUP-14 | E5: Measuring Cups Steel | F5: Receipts | G5: FBA15TH77146 | H5: 705 | I5: DFW6 | J5: SELLABLE | L5: US | M5: 0 | N5: 0 | O5: =IFERROR(VLOOKUP(K5,'Reason codes'!$A$2:$B$40,2,FALSE),"") | P5: =IF(AND(ISNUMBER(SEARCH("adjust",F5)),OR(O5="warehouse_lost",O5="warehouse_damaged",O5="carrier_damaged",O5="transit_lost")),"yes","no") | Q5: =IF(P5="yes",IF(N5<>"",N5,MAX(0,-H5)),0)
A6: 2026-03-11 | B6: X0TH0006 | C6: B0TH006KX | D6: TH-BAMCUT-06 | E6: Bamboo Cutting Board M | F6: Receipts | G6: FBA15TH77055 | H6: 1080 | I6: LAX9 | J6: SELLABLE | L6: US | M6: 0 | N6: 0 | O6: =IFERROR(VLOOKUP(K6,'Reason codes'!$A$2:$B$40,2,FALSE),"") | P6: =IF(AND(ISNUMBER(SEARCH("adjust",F6)),OR(O6="warehouse_lost",O6="warehouse_damaged",O6="carrier_damaged",O6="transit_lost")),"yes","no") | Q6: =IF(P6="yes",IF(N6<>"",N6,MAX(0,-H6)),0)
A7: 2026-03-15 | B7: X0TH0014 | C7: B0TH014KX | D7: TH-MEACUP-14 | E7: Measuring Cups Steel | F7: Receipts | G7: FBA15TH77145 | H7: 705 | I7: PHX7 | J7: SELLABLE | L7: US | M7: 0 | N7: 0 | O7: =IFERROR(VLOOKUP(K7,'Reason codes'!$A$2:$B$40,2,FALSE),"") | P7: =IF(AND(ISNUMBER(SEARCH("adjust",F7)),OR(O7="warehouse_lost",O7="warehouse_damaged",O7="carrier_damaged",O7="transit_lost")),"yes","no") | Q7: =IF(P7="yes",IF(N7<>"",N7,MAX(0,-H7)),0)
A8: 2026-03-22 | B8: X0TH0023 | C8: B0TH023KX | D8: TH-TRICOR-23 | E8: Trivet Cork Set | F8: Receipts | G8: FBA15TH77243 | H8: 915 | I8: ONT8 | J8: SELLABLE | L8: US | M8: 0 | N8: 0 | O8: =IFERROR(VLOOKUP(K8,'Reason codes'!$A$2:$B$40,2,FALSE),"") | P8: =IF(AND(ISNUMBER(SEARCH("adjust",F8)),OR(O8="warehouse_lost",O8="warehouse_damaged",O8="carrier_damaged",O8="transit_lost")),"yes","no") | Q8: =IF(P8="yes",IF(N8<>"",N8,MAX(0,-H8)),0)
A9: 2026-03-23 | B9: X0TH0002 | C9: B0TH002KX | D9: TH-CASIRO-02 | E9: Cast Iron Skillet 12in | F9: Receipts | G9: FBA15TH77010 | H9: 615 | I9: LAX9 | J9: SELLABLE | L9: US | M9: 0 | N9: 0 | O9: =IFERROR(VLOOKUP(K9,'Reason codes'!$A$2:$B$40,2,FALSE),"") | P9: =IF(AND(ISNUMBER(SEARCH("adjust",F9)),OR(O9="warehouse_lost",O9="warehouse_damaged",O9="carrier_damaged",O9="transit_lost")),"yes","no") | Q9: =IF(P9="yes",IF(N9<>"",N9,MAX(0,-H9)),0)
A10: 2026-03-23 | B10: X0TH0011 | C10: B0TH011KX | D10: TH-KNISHA-11 | E10: Knife Sharpener Whetstone | F10: Receipts | G10: FBA15TH77108 | H10: 570 | I10: LAX9 | J10: SELLABLE | L10: US | M10: 0 | N10: 0 | O10: =IFERROR(VLOOKUP(K10,'Reason codes'!$A$2:$B$40,2,FALSE),"") | P10: =IF(AND(ISNUMBER(SEARCH("adjust",F10)),OR(O10="warehouse_lost",O10="warehouse_damaged",O10="carrier_damaged",O10="transit_lost")),"yes","no") | Q10: =IF(P10="yes",IF(N10<>"",N10,MAX(0,-H10)),0)
A11: 2026-03-26 | B11: X0TH0013 | C11: B0TH013KX | D11: TH-SILSPA-13 | E11: Silicone Spatula Set | F11: Receipts | G11: FBA15TH77135 | H11: 1350 | I11: PHX7 | J11: SELLABLE | L11: US | M11: 0 | N11: 0 | O11: =IFERROR(VLOOKUP(K11,'Reason codes'!$A$2:$B$40,2,FALSE),"") | P11: =IF(AND(ISNUMBER(SEARCH("adjust",F11)),OR(O11="warehouse_lost",O11="warehouse_damaged",O11="carrier_damaged",O11="transit_lost")),"yes","no") | Q11: =IF(P11="yes",IF(N11<>"",N11,MAX(0,-H11)),0)
A12: 2026-03-27 | B12: X0TH0003 | C12: B0TH003KX | D12: TH-ENADUT-03 | E12: Enamel Dutch Oven 5qt | F12: Receipts | G12: FBA15TH77025 | H12: 390 | I12: LAX9 | J12: SELLABLE | L12: US | M12: 0 | N12: 0 | O12: =IFERROR(VLOOKUP(K12,'Reason codes'!$A$2:$B$40,2,FALSE),"") | P12: =IF(AND(ISNUMBER(SEARCH("adjust",F12)),OR(O12="warehouse_lost",O12="warehouse_damaged",O12="carrier_damaged",O12="transit_lost")),"yes","no") | Q12: =IF(P12="yes",IF(N12<>"",N12,MAX(0,-H12)),0)
A13: 2026-03-27 | B13: X0TH0010 | C13: B0TH010KX | D13: TH-BREKNI-10 | E13: Bread Knife 10in | F13: Receipts | G13: FBA15TH77096 | H13: 420 | I13: MDW2 | J13: SELLABLE | L13: US | M13: 0 | N13: 0 | O13: =IFERROR(VLOOKUP(K13,'Reason codes'!$A$2:$B$40,2,FALSE),"") | P13: =IF(AND(ISNUMBER(SEARCH("adjust",F13)),OR(O13="warehouse_lost",O13="warehouse_damaged",O13="carrier_damaged",O13="transit_lost")),"yes","no") | Q13: =IF(P13="yes",IF(N13<>"",N13,MAX(0,-H13)),0)
... A27: 2026-05-13 | B27: X0TH0024 | C27: B0TH024KX | D27: TH-KITTOW-24 | E27: Kitchen Towels Linen 4pk | F27: Receipts | G27: FBA15TH77252 | H27: 510 | I27: PHX7 | J27: SELLABLE | L27: US | M27: 0 | N27: 0 | O27: =IFERROR(VLOOKUP(K27,'Reason codes'!$A$2:$B$40,2,FALSE),"") | P27: =IF(AND(ISNUMBER(SEARCH("adjust",F27)),OR(O27="warehouse_lost",O27="warehouse_damaged",O27="carrier_damaged",O27="transit_lost")),"yes","no") | Q27: =IF(P27="yes",IF(N27<>"",N27,MAX(0,-H27)),0)
A28: 2026-05-15 | B28: X0TH0003 | C28: B0TH003KX | D28: TH-ENADUT-03 | E28: Enamel Dutch Oven 5qt | F28: Adjustments | G28: ADJ-77029 | H28: -4 | I28: MDW2 | J28: SELLABLE | K28: N | L28: US | M28: 4 | O28: =IFERROR(VLOOKUP(K28,'Reason codes'!$A$2:$B$40,2,FALSE),"") | P28: =IF(AND(ISNUMBER(SEARCH("adjust",F28)),OR(O28="warehouse_lost",O28="warehouse_damaged",O28="carrier_damaged",O28="transit_lost")),"yes","no") | Q28: =IF(P28="yes",IF(N28<>"",N28,MAX(0,-H28)),0)
A29: 2026-05-18 | B29: X0TH0001 | C29: B0TH001KX | D29: TH-CASIRO-01 | E29: Cast Iron Skillet 10in | F29: Adjustments | G29: ADJ-77002 | H29: -3 | I29: PHX7 | J29: SELLABLE | K29: N | L29: US | M29: 0 | N29: 3 | O29: =IFERROR(VLOOKUP(K29,'Reason codes'!$A$2:$B$40,2,FALSE),"") | P29: =IF(AND(ISNUMBER(SEARCH("adjust",F29)),OR(O29="warehouse_lost",O29="warehouse_damaged",O29="carrier_damaged",O29="transit_lost")),"yes","no") | Q29: =IF(P29="yes",IF(N29<>"",N29,MAX(0,-H29)),0)
A30: 2026-05-20 | B30: X0TH0005 | C30: B0TH005KX | D30: TH-BAMCUT-05 | E30: Bamboo Cutting Board L | F30: Adjustments | G30: ADJ-77050 | H30: -2 | I30: DFW6 | J30: SELLABLE | K30: N | L30: US | M30: 2 | O30: =IFERROR(VLOOKUP(K30,'Reason codes'!$A$2:$B$40,2,FALSE),"") | P30: =IF(AND(ISNUMBER(SEARCH("adjust",F30)),OR(O30="warehouse_lost",O30="warehouse_damaged",O30="carrier_damaged",O30="transit_lost")),"yes","no") | Q30: =IF(P30="yes",IF(N30<>"",N30,MAX(0,-H30)),0)
A31: 2026-05-20 | B31: X0TH0009 | C31: B0TH009KX | D31: TH-PARKNI-09 | E31: Paring Knife 3.5in | F31: Adjustments | G31: ADJ-77089 | H31: -2 | I31: MDW2 | J31: SELLABLE | K31: N | L31: US | M31: 0 | N31: 2 | O31: =IFERROR(VLOOKUP(K31,'Reason codes'!$A$2:$B$40,2,FALSE),"") | P31: =IF(AND(ISNUMBER(SEARCH("adjust",F31)),OR(O31="warehouse_lost",O31="warehouse_damaged",O31="carrier_damaged",O31="transit_lost")),"yes","no") | Q31: =IF(P31="yes",IF(N31<>"",N31,MAX(0,-H31)),0)
A32: 2026-05-21 | B32: X0TH0004 | C32: B0TH004KX | D32: TH-CARSTE-04 | E32: Carbon Steel Wok | F32: Receipts | G32: FBA15TH77035 | H32: 450 | I32: LAX9 | J32: SELLABLE | L32: US | M32: 0 | N32: 0 | O32: =IFERROR(VLOOKUP(K32,'Reason codes'!$A$2:$B$40,2,FALSE),"") | P32: =IF(AND(ISNUMBER(SEARCH("adjust",F32)),OR(O32="warehouse_lost",O32="warehouse_damaged",O32="carrier_damaged",O32="transit_lost")),"yes","no") | Q32: =IF(P32="yes",IF(N32<>"",N32,MAX(0,-H32)),0)
A33: 2026-05-23 | B33: X0TH0008 | C33: B0TH008KX | D33: TH-CHEKNI-08 | E33: Chef Knife 8in | F33: Receipts | G33: FBA15TH77075 | H33: 675 | I33: ONT8 | J33: SELLABLE | L33: US | M33: 0 | N33: 0 | O33: =IFERROR(VLOOKUP(K33,'Reason codes'!$A$2:$B$40,2,FALSE),"") | P33: =IF(AND(ISNUMBER(SEARCH("adjust",F33)),OR(O33="warehouse_lost",O33="warehouse_damaged",O33="carrier_damaged",O33="transit_lost")),"yes","no") | Q33: =IF(P33="yes",IF(N33<>"",N33,MAX(0,-H33)),0)
A34: 2026-05-25 | B34: X0TH0006 | C34: B0TH006KX | D34: TH-BAMCUT-06 | E34: Bamboo Cutting Board M | F34: Adjustments | G34: ADJ-77058 | H34: -7 | I34: PHX7 | J34: SELLABLE | K34: N | L34: US | M34: 0 | N34: 7 | O34: =IFERROR(VLOOKUP(K34,'Reason codes'!$A$2:$B$40,2,FALSE),"") | P34: =IF(AND(ISNUMBER(SEARCH("adjust",F34)),OR(O34="warehouse_lost",O34="warehouse_damaged",O34="carrier_damaged",O34="transit_lost")),"yes","no") | Q34: =IF(P34="yes",IF(N34<>"",N34,MAX(0,-H34)),0)
A35: 2026-05-26 | B35: X0TH0015 | C35: B0TH015KX | D35: TH-SALCEL-15 | E35: Salt Cellar Acacia | F35: Adjustments | G35: ADJ-77163 | H35: -8 | I35: MDW2 | J35: SELLABLE | K35: N | L35: US | M35: 0 | N35: 8 | O35: =IFERROR(VLOOKUP(K35,'Reason codes'!$A$2:$B$40,2,FALSE),"") | P35: =IF(AND(ISNUMBER(SEARCH("adjust",F35)),OR(O35="warehouse_lost",O35="warehouse_damaged",O35="carrier_damaged",O35="transit_lost")),"yes","no") | Q35: =IF(P35="yes",IF(N35<>"",N35,MAX(0,-H35)),0)
A36: 2026-05-27 | B36: X0TH0010 | C36: B0TH010KX | D36: TH-BREKNI-10 | E36: Bread Knife 10in | F36: Adjustments | G36: ADJ-77099 | H36: -5 | I36: ONT8 | J36: SELLABLE | K36: N | L36: US | M36: 5 | O36: =IFERROR(VLOOKUP(K36,'Reason codes'!$A$2:$B$40,2,FALSE),"") | P36: =IF(AND(ISNUMBER(SEARCH("adjust",F36)),OR(O36="warehouse_lost",O36="warehouse_damaged",O36="carrier_damaged",O36="transit_lost")),"yes","no") | Q36: =IF(P36="yes",IF(N36<>"",N36,MAX(0,-H36)),0)
A37: 2026-05-30 | B37: X0TH0011 | C37: B0TH011KX | D37: TH-KNISHA-11 | E37: Knife Sharpener Whetstone | F37: Adjustments | G37: ADJ-77113 | H37: -3 | I37: LAX9 | J37: SELLABLE | K37: N | L37: US | M37: 0 | N37: 3 | O37: =IFERROR(VLOOKUP(K37,'Reason codes'!$A$2:$B$40,2,FALSE),"") | P37: =IF(AND(ISNUMBER(SEARCH("adjust",F37)),OR(O37="warehouse_lost",O37="warehouse_damaged",O37="carrier_damaged",O37="transit_lost")),"yes","no") | Q37: =IF(P37="yes",IF(N37<>"",N37,MAX(0,-H37)),0)
A38: 2026-05-30 | B38: X0TH0014 | C38: B0TH014KX | D38: TH-MEACUP-14 | E38: Measuring Cups Steel | F38: Adjustments | G38: ADJ-77150 | H38: -8 | I38: LAX9 | J38: SELLABLE | K38: N | L38: US | M38: 0 | N38: 8 | O38: =IFERROR(VLOOKUP(K38,'Reason codes'!$A$2:$B$40,2,FALSE),"") | P38: =IF(AND(ISNUMBER(SEARCH("adjust",F38)),OR(O38="warehouse_lost",O38="warehouse_damaged",O38="carrier_damaged",O38="transit_lost")),"yes","no") | Q38: =IF(P38="yes",IF(N38<>"",N38,MAX(0,-H38)),0)
A39: 2026-06-01 | B39: X0TH0008 | C39: B0TH008KX | D39: TH-CHEKNI-08 | E39: Chef Knife 8in | F39: Adjustments | G39: ADJ-77080 | H39: -4 | I39: LAX9 | J39: SELLABLE | K39: N | L39: US | M39: 0 | N39: 4 | O39: =IFERROR(VLOOKUP(K39,'Reason codes'!$A$2:$B$40,2,FALSE),"") | P39: =IF(AND(ISNUMBER(SEARCH("adjust",F39)),OR(O39="warehouse_lost",O39="warehouse_damaged",O39="carrier_damaged",O39="transit_lost")),"yes","no") | Q39: =IF(P39="yes",IF(N39<>"",N39,MAX(0,-H39)),0)
A40: 2026-06-01 | B40: X0TH0010 | C40: B0TH010KX | D40: TH-BREKNI-10 | E40: Bread Knife 10in | F40: Receipts | G40: FBA15TH77097 | H40: 420 | I40: MDW2 | J40: SELLABLE | L40: US | M40: 0 | N40: 0 | O40: =IFERROR(VLOOKUP(K40,'Reason codes'!$A$2:$B$40,2,FALSE),"") | P40: =IF(AND(ISNUMBER(SEARCH("adjust",F40)),OR(O40="warehouse_lost",O40="warehouse_damaged",O40="carrier_damaged",O40="transit_lost")),"yes","no") | Q40: =IF(P40="yes",IF(N40<>"",N40,MAX(0,-H40)),0)
A41: 2026-06-03 | B41: X0TH0007 | C41: B0TH007KX | D41: TH-WALSER-07 | E41: Walnut Serving Tray | F41: Receipts | G41: FBA15TH77065 | H41: 285 | I41: LAX9 | J41: SELLABLE | L41: US | M41: 0 | N41: 0 | O41: =IFERROR(VLOOKUP(K41,'Reason codes'!$A$2:$B$40,2,FALSE),"") | P41: =IF(AND(ISNUMBER(SEARCH("adjust",F41)),OR(O41="warehouse_lost",O41="warehouse_damaged",O41="carrier_damaged",O41="transit_lost")),"yes","no") | Q41: =IF(P41="yes",IF(N41<>"",N41,MAX(0,-H41)),0)
A42: 2026-06-03 | B42: X0TH0024 | C42: B0TH024KX | D42: TH-KITTOW-24 | E42: Kitchen Towels Linen 4pk | F42: Receipts | G42: FBA15TH77251 | H42: 510 | I42: DFW6 | J42: SELLABLE | L42: US | M42: 0 | N42: 0 | O42: =IFERROR(VLOOKUP(K42,'Reason codes'!$A$2:$B$40,2,FALSE),"") | P42: =IF(AND(ISNUMBER(SEARCH("adjust",F42)),OR(O42="warehouse_lost",O42="warehouse_damaged",O42="carrier_damaged",O42="transit_lost")),"yes","no") | Q42: =IF(P42="yes",IF(N42<>"",N42,MAX(0,-H42)),0)
A43: 2026-06-04 | B43: X0TH0016 | C43: B0TH016KX | D43: TH-PEPMIL-16 | E43: Pepper Mill Walnut | F43: Adjustments | G43: ADJ-77173 | H43: -7 | I43: DFW6 | J43: SELLABLE | K43: N | L43: US | M43: 7 | O43: =IFERROR(VLOOKUP(K43,'Reason codes'!$A$2:$B$40,2,FALSE),"") | P43: =IF(AND(ISNUMBER(SEARCH("adjust",F43)),OR(O43="warehouse_lost",O43="warehouse_damaged",O43="carrier_damaged",O43="transit_lost")),"yes","no") | Q43: =IF(P43="yes",IF(N43<>"",N43,MAX(0,-H43)),0)
A44: 2026-06-09 | B44: X0TH0007 | C44: B0TH007KX | D44: TH-WALSER-07 | E44: Walnut Serving Tray | F44: Adjustments | G44: ADJ-77070 | H44: -6 | I44: MDW2 | J44: SELLABLE | K44: N | L44: US | M44: 6 | O44: =IFERROR(VLOOKUP(K44,'Reason codes'!$A$2:$B$40,2,FALSE),"") | P44: =IF(AND(ISNUMBER(SEARCH("adjust",F44)),OR(O44="warehouse_lost",O44="warehouse_damaged",O44="carrier_damaged",O44="transit_lost")),"yes","no") | Q44: =IF(P44="yes",IF(N44<>"",N44,MAX(0,-H44)),0)
A45: 2026-06-09 | B45: X0TH0019 | C45: B0TH019KX | D45: TH-COFCAN-19 | E45: Coffee Canister Airtight | F45: Adjustments | G45: ADJ-77202 | H45: -4 | I45: MDW2 | J45: SELLABLE | K45: N | L45: US | M45: 4 | O45: =IFERROR(VLOOKUP(K45,'Reason codes'!$A$2:$B$40,2,FALSE),"") | P45: =IF(AND(ISNUMBER(SEARCH("adjust",F45)),OR(O45="warehouse_lost",O45="warehouse_damaged",O45="carrier_damaged",O45="transit_lost")),"yes","no") | Q45: =IF(P45="yes",IF(N45<>"",N45,MAX(0,-H45)),0)
A46: 2026-06-10 | B46: X0TH0020 | C46: B0TH020KX | D46: TH-TEAINF-20 | E46: Tea Infuser Mug | F46: Receipts | G46: FBA15TH77208 | H46: 570 | I46: MDW2 | J46: SELLABLE | L46: US | M46: 0 | N46: 0 | O46: =IFERROR(VLOOKUP(K46,'Reason codes'!$A$2:$B$40,2,FALSE),"") | P46: =IF(AND(ISNUMBER(SEARCH("adjust",F46)),OR(O46="warehouse_lost",O46="warehouse_damaged",O46="carrier_damaged",O46="transit_lost")),"yes","no") | Q46: =IF(P46="yes",IF(N46<>"",N46,MAX(0,-H46)),0)
A47: 2026-06-15 | B47: X0TH0009 | C47: B0TH009KX | D47: TH-PARKNI-09 | E47: Paring Knife 3.5in | F47: Receipts | G47: FBA15TH77086 | H47: 915 | I47: ONT8 | J47: SELLABLE | L47: US | M47: 0 | N47: 0 | O47: =IFERROR(VLOOKUP(K47,'Reason codes'!$A$2:$B$40,2,FALSE),"") | P47: =IF(AND(ISNUMBER(SEARCH("adjust",F47)),OR(O47="warehouse_lost",O47="warehouse_damaged",O47="carrier_damaged",O47="transit_lost")),"yes","no") | Q47: =IF(P47="yes",IF(N47<>"",N47,MAX(0,-H47)),0)
A48: 2026-06-15 | B48: X0TH0022 | C48: B0TH022KX | D48: TH-OVEMIT-22 | E48: Oven Mitts Aramid Pair | F48: Adjustments | G48: ADJ-77235 | H48: -6 | I48: DFW6 | J48: SELLABLE | K48: N | L48: US | M48: 0 | N48: 6 | O48: =IFERROR(VLOOKUP(K48,'Reason codes'!$A$2:$B$40,2,FALSE),"") | P48: =IF(AND(ISNUMBER(SEARCH("adjust",F48)),OR(O48="warehouse_lost",O48="warehouse_damaged",O48="carrier_damaged",O48="transit_lost")),"yes","no") | Q48: =IF(P48="yes",IF(N48<>"",N48,MAX(0,-H48)),0)
A49: 2026-06-18 | B49: X0TH0019 | C49: B0TH019KX | D49: TH-COFCAN-19 | E49: Coffee Canister Airtight | F49: Receipts | G49: FBA15TH77196 | H49: 645 | I49: ONT8 | J49: SELLABLE | L49: US | M49: 0 | N49: 0 | O49: =IFERROR(VLOOKUP(K49,'Reason codes'!$A$2:$B$40,2,FALSE),"") | P49: =IF(AND(ISNUMBER(SEARCH("adjust",F49)),OR(O49="warehouse_lost",O49="warehouse_damaged",O49="carrier_damaged",O49="transit_lost")),"yes","no") | Q49: =IF(P49="yes",IF(N49<>"",N49,MAX(0,-H49)),0)
A50: 2026-06-20 | B50: X0TH0004 | C50: B0TH004KX | D50: TH-CARSTE-04 | E50: Carbon Steel Wok | F50: Adjustments | G50: ADJ-77039 | H50: -4 | I50: LAX9 | J50: SELLABLE | K50: N | L50: US | M50: 0 | N50: 4 | O50: =IFERROR(VLOOKUP(K50,'Reason codes'!$A$2:$B$40,2,FALSE),"") | P50: =IF(AND(ISNUMBER(SEARCH("adjust",F50)),OR(O50="warehouse_lost",O50="warehouse_damaged",O50="carrier_damaged",O50="transit_lost")),"yes","no") | Q50: =IF(P50="yes",IF(N50<>"",N50,MAX(0,-H50)),0)
A51: 2026-06-20 | B51: X0TH0020 | C51: B0TH020KX | D51: TH-TEAINF-20 | E51: Tea Infuser Mug | F51: Adjustments | G51: ADJ-77212 | H51: -4 | I51: LAX9 | J51: SELLABLE | K51: N | L51: US | M51: 4 | O51: =IFERROR(VLOOKUP(K51,'Reason codes'!$A$2:$B$40,2,FALSE),"") | P51: =IF(AND(ISNUMBER(SEARCH("adjust",F51)),OR(O51="warehouse_lost",O51="warehouse_damaged",O51="carrier_damaged",O51="transit_lost")),"yes","no") | Q51: =IF(P51="yes",IF(N51<>"",N51,MAX(0,-H51)),0)
A52: 2026-06-22 | B52: X0TH0024 | C52: B0TH024KX | D52: TH-KITTOW-24 | E52: Kitchen Towels Linen 4pk | F52: Adjustments | G52: ADJ-77256 | H52: -6 | I52: LAX9 | J52: SELLABLE | K52: N | L52: US | M52: 6 | O52: =IFERROR(VLOOKUP(K52,'Reason codes'!$A$2:$B$40,2,FALSE),"") | P52: =IF(AND(ISNUMBER(SEARCH("adjust",F52)),OR(O52="warehouse_lost",O52="warehouse_damaged",O52="carrier_damaged",O52="transit_lost")),"yes","no") | Q52: =IF(P52="yes",IF(N52<>"",N52,MAX(0,-H52)),0)
A53: 2026-06-25 | B53: X0TH0017 | C53: B0TH017KX | D53: TH-FREPRE-17 | E53: French Press 34oz | F53: Receipts | G53: FBA15TH77178 | H53: 585 | I53: LAX9 | J53: SELLABLE | L53: US | M53: 0 | N53: 0 | O53: =IFERROR(VLOOKUP(K53,'Reason codes'!$A$2:$B$40,2,FALSE),"") | P53: =IF(AND(ISNUMBER(SEARCH("adjust",F53)),OR(O53="warehouse_lost",O53="warehouse_damaged",O53="carrier_damaged",O53="transit_lost")),"yes","no") | Q53: =IF(P53="yes",IF(N53<>"",N53,MAX(0,-H53)),0)
A54: 2026-06-27 | B54: X0TH0003 | C54: B0TH003KX | D54: TH-ENADUT-03 | E54: Enamel Dutch Oven 5qt | F54: Receipts | G54: FBA15TH77024 | H54: 390 | I54: DFW6 | J54: SELLABLE | L54: US | M54: 0 | N54: 0 | O54: =IFERROR(VLOOKUP(K54,'Reason codes'!$A$2:$B$40,2,FALSE),"") | P54: =IF(AND(ISNUMBER(SEARCH("adjust",F54)),OR(O54="warehouse_lost",O54="warehouse_damaged",O54="carrier_damaged",O54="transit_lost")),"yes","no") | Q54: =IF(P54="yes",IF(N54<>"",N54,MAX(0,-H54)),0)
A55: 2026-07-05 | B55: X0TH0007 | C55: B0TH007KX | D55: TH-WALSER-07 | E55: Walnut Serving Tray | F55: Adjustments | G55: ADJ-77069 | H55: -9 | I55: ONT8 | J55: DAMAGED | K55: K | L55: US | M55: 9 | O55: =IFERROR(VLOOKUP(K55,'Reason codes'!$A$2:$B$40,2,FALSE),"") | P55: =IF(AND(ISNUMBER(SEARCH("adjust",F55)),OR(O55="warehouse_lost",O55="warehouse_damaged",O55="carrier_damaged",O55="transit_lost")),"yes","no") | Q55: =IF(P55="yes",IF(N55<>"",N55,MAX(0,-H55)),0)
A56: 2026-07-05 | B56: X0TH0008 | C56: B0TH008KX | D56: TH-CHEKNI-08 | E56: Chef Knife 8in | F56: Adjustments | G56: ADJ-77079 | H56: -6 | I56: DFW6 | J56: DAMAGED | K56: H | L56: US | M56: 6 | O56: =IFERROR(VLOOKUP(K56,'Reason codes'!$A$2:$B$40,2,FALSE),"") | P56: =IF(AND(ISNUMBER(SEARCH("adjust",F56)),OR(O56="warehouse_lost",O56="warehouse_damaged",O56="carrier_damaged",O56="transit_lost")),"yes","no") | Q56: =IF(P56="yes",IF(N56<>"",N56,MAX(0,-H56)),0)
A57: 2026-07-05 | B57: X0TH0018 | C57: B0TH018KX | D57: TH-POUOVE-18 | E57: Pour Over Kettle Gooseneck | F57: Receipts | G57: FBA15TH77188 | H57: 360 | I57: LAX9 | J57: SELLABLE | L57: US | M57: 0 | N57: 0 | O57: =IFERROR(VLOOKUP(K57,'Reason codes'!$A$2:$B$40,2,FALSE),"") | P57: =IF(AND(ISNUMBER(SEARCH("adjust",F57)),OR(O57="warehouse_lost",O57="warehouse_damaged",O57="carrier_damaged",O57="transit_lost")),"yes","no") | Q57: =IF(P57="yes",IF(N57<>"",N57,MAX(0,-H57)),0)
A58: 2026-07-06 | B58: X0TH0014 | C58: B0TH014KX | D58: TH-MEACUP-14 | E58: Measuring Cups Steel | F58: Adjustments | G58: ADJ-77149 | H58: -12 | I58: LAX9 | J58: DAMAGED | K58: K | L58: US | M58: 12 | O58: =IFERROR(VLOOKUP(K58,'Reason codes'!$A$2:$B$40,2,FALSE),"") | P58: =IF(AND(ISNUMBER(SEARCH("adjust",F58)),OR(O58="warehouse_lost",O58="warehouse_damaged",O58="carrier_damaged",O58="transit_lost")),"yes","no") | Q58: =IF(P58="yes",IF(N58<>"",N58,MAX(0,-H58)),0)
A59: 2026-07-06 | B59: X0TH0016 | C59: B0TH016KX | D59: TH-PEPMIL-16 | E59: Pepper Mill Walnut | F59: Adjustments | G59: ADJ-77172 | H59: -13 | I59: DFW6 | J59: DAMAGED | K59: H | L59: US | M59: 13 | O59: =IFERROR(VLOOKUP(K59,'Reason codes'!$A$2:$B$40,2,FALSE),"") | P59: =IF(AND(ISNUMBER(SEARCH("adjust",F59)),OR(O59="warehouse_lost",O59="warehouse_damaged",O59="carrier_damaged",O59="transit_lost")),"yes","no") | Q59: =IF(P59="yes",IF(N59<>"",N59,MAX(0,-H59)),0)
A60: 2026-07-06 | B60: X0TH0022 | C60: B0TH022KX | D60: TH-OVEMIT-22 | E60: Oven Mitts Aramid Pair | F60: Adjustments | G60: ADJ-77234 | H60: -4 | I60: DFW6 | J60: DAMAGED | K60: H | L60: US | M60: 4 | O60: =IFERROR(VLOOKUP(K60,'Reason codes'!$A$2:$B$40,2,FALSE),"") | P60: =IF(AND(ISNUMBER(SEARCH("adjust",F60)),OR(O60="warehouse_lost",O60="warehouse_damaged",O60="carrier_damaged",O60="transit_lost")),"yes","no") | Q60: =IF(P60="yes",IF(N60<>"",N60,MAX(0,-H60)),0)
A61: 2026-07-07 | B61: X0TH0010 | C61: B0TH010KX | D61: TH-BREKNI-10 | E61: Bread Knife 10in | F61: Adjustments | G61: ADJ-77098 | H61: -7 | I61: LAX9 | J61: SELLABLE | K61: 6 | L61: US | M61: 7 | O61: =IFERROR(VLOOKUP(K61,'Reason codes'!$A$2:$B$40,2,FALSE),"") | P61: =IF(AND(ISNUMBER(SEARCH("adjust",F61)),OR(O61="warehouse_lost",O61="warehouse_damaged",O61="carrier_damaged",O61="transit_lost")),"yes","no") | Q61: =IF(P61="yes",IF(N61<>"",N61,MAX(0,-H61)),0)
A62: 2026-07-07 | B62: X0TH0011 | C62: B0TH011KX | D62: TH-KNISHA-11 | E62: Knife Sharpener Whetstone | F62: Adjustments | G62: ADJ-77112 | H62: -4 | I62: DFW6 | J62: DAMAGED | K62: K | L62: US | M62: 4 | O62: =IFERROR(VLOOKUP(K62,'Reason codes'!$A$2:$B$40,2,FALSE),"") | P62: =IF(AND(ISNUMBER(SEARCH("adjust",F62)),OR(O62="warehouse_lost",O62="warehouse_damaged",O62="carrier_damaged",O62="transit_lost")),"yes","no") | Q62: =IF(P62="yes",IF(N62<>"",N62,MAX(0,-H62)),0)
A63: 2026-07-08 | B63: X0TH0004 | C63: B0TH004KX | D63: TH-CARSTE-04 | E63: Carbon Steel Wok | F63: Adjustments | G63: ADJ-77038 | H63: -7 | I63: DFW6 | J63: SELLABLE | K63: 6 | L63: US | M63: 0 | N63: 7 | O63: =IFERROR(VLOOKUP(K63,'Reason codes'!$A$2:$B$40,2,FALSE),"") | P63: =IF(AND(ISNUMBER(SEARCH("adjust",F63)),OR(O63="warehouse_lost",O63="warehouse_damaged",O63="carrier_damaged",O63="transit_lost")),"yes","no") | Q63: =IF(P63="yes",IF(N63<>"",N63,MAX(0,-H63)),0)
A64: 2026-07-08 | B64: X0TH0023 | C64: B0TH023KX | D64: TH-TRICOR-23 | E64: Trivet Cork Set | F64: Receipts | G64: FBA15TH77242 | H64: 915 | I64: ONT8 | J64: SELLABLE | L64: US | M64: 0 | N64: 0 | O64: =IFERROR(VLOOKUP(K64,'Reason codes'!$A$2:$B$40,2,FALSE),"") | P64: =IF(AND(ISNUMBER(SEARCH("adjust",F64)),OR(O64="warehouse_lost",O64="warehouse_damaged",O64="carrier_damaged",O64="transit_lost")),"yes","no") | Q64: =IF(P64="yes",IF(N64<>"",N64,MAX(0,-H64)),0)
A65: 2026-07-09 | B65: X0TH0022 | C65: B0TH022KX | D65: TH-OVEMIT-22 | E65: Oven Mitts Aramid Pair | F65: Adjustments | G65: ADJ-77232 | H65: -19 | I65: MDW2 | J65: SELLABLE | K65: M | L65: US | M65: 19 | O65: =IFERROR(VLOOKUP(K65,'Reason codes'!$A$2:$B$40,2,FALSE),"") | P65: =IF(AND(ISNUMBER(SEARCH("adjust",F65)),OR(O65="warehouse_lost",O65="warehouse_damaged",O65="carrier_damaged",O65="transit_lost")),"yes","no") | Q65: =IF(P65="yes",IF(N65<>"",N65,MAX(0,-H65)),0)
A66: 2026-07-10 | B66: X0TH0003 | C66: B0TH003KX | D66: TH-ENADUT-03 | E66: Enamel Dutch Oven 5qt | F66: Adjustments | G66: ADJ-77028 | H66: -8 | I66: LAX9 | J66: DAMAGED | K66: H | L66: US | M66: 8 | O66: =IFERROR(VLOOKUP(K66,'Reason codes'!$A$2:$B$40,2,FALSE),"") | P66: =IF(AND(ISNUMBER(SEARCH("adjust",F66)),OR(O66="warehouse_lost",O66="warehouse_damaged",O66="carrier_damaged",O66="transit_lost")),"yes","no") | Q66: =IF(P66="yes",IF(N66<>"",N66,MAX(0,-H66)),0)
A67: 2026-07-10 | B67: X0TH0005 | C67: B0TH005KX | D67: TH-BAMCUT-05 | E67: Bamboo Cutting Board L | F67: Adjustments | G67: ADJ-77049 | H67: -6 | I67: MDW2 | J67: DAMAGED | K67: H | L67: US | M67: 6 | O67: =IFERROR(VLOOKUP(K67,'Reason codes'!$A$2:$B$40,2,FALSE),"") | P67: =IF(AND(ISNUMBER(SEARCH("adjust",F67)),OR(O67="warehouse_lost",O67="warehouse_damaged",O67="carrier_damaged",O67="transit_lost")),"yes","no") | Q67: =IF(P67="yes",IF(N67<>"",N67,MAX(0,-H67)),0)
A68: 2026-07-10 | B68: X0TH0012 | C68: B0TH012KX | D68: TH-STAMIX-12 | E68: Stainless Mixing Bowls 5pc | F68: Adjustments | G68: ADJ-77125 | H68: -18 | I68: ONT8 | J68: SELLABLE | K68: M | L68: US | M68: 0 | N68: 18 | O68: =IFERROR(VLOOKUP(K68,'Reason codes'!$A$2:$B$40,2,FALSE),"") | P68: =IF(AND(ISNUMBER(SEARCH("adjust",F68)),OR(O68="warehouse_lost",O68="warehouse_damaged",O68="carrier_damaged",O68="transit_lost")),"yes","no") | Q68: =IF(P68="yes",IF(N68<>"",N68,MAX(0,-H68)),0)
A69: 2026-07-10 | B69: X0TH0017 | C69: B0TH017KX | D69: TH-FREPRE-17 | E69: French Press 34oz | F69: Adjustments | G69: ADJ-77181 | H69: -8 | I69: PHX7 | J69: DAMAGED | K69: K | L69: US | M69: 8 | O69: =IFERROR(VLOOKUP(K69,'Reason codes'!$A$2:$B$40,2,FALSE),"") | P69: =IF(AND(ISNUMBER(SEARCH("adjust",F69)),OR(O69="warehouse_lost",O69="warehouse_damaged",O69="carrier_damaged",O69="transit_lost")),"yes","no") | Q69: =IF(P69="yes",IF(N69<>"",N69,MAX(0,-H69)),0)
A70: 2026-07-10 | B70: X0TH0019 | C70: B0TH019KX | D70: TH-COFCAN-19 | E70: Coffee Canister Airtight | F70: Adjustments | G70: ADJ-77201 | H70: -9 | I70: LAX9 | J70: DAMAGED | K70: H | L70: US | M70: 0 | N70: 9 | O70: =IFERROR(VLOOKUP(K70,'Reason codes'!$A$2:$B$40,2,FALSE),"") | P70: =IF(AND(ISNUMBER(SEARCH("adjust",F70)),OR(O70="warehouse_lost",O70="warehouse_damaged",O70="carrier_damaged",O70="transit_lost")),"yes","no") | Q70: =IF(P70="yes",IF(N70<>"",N70,MAX(0,-H70)),0)
A71: 2026-07-10 | B71: X0TH0021 | C71: B0TH021KX | D71: TH-APRWAX-21 | E71: Apron Waxed Canvas | F71: Adjustments | G71: ADJ-77222 | H71: -21 | I71: MDW2 | J71: SELLABLE | K71: M | L71: US | M71: 21 | O71: =IFERROR(VLOOKUP(K71,'Reason codes'!$A$2:$B$40,2,FALSE),"") | P71: =IF(AND(ISNUMBER(SEARCH("adjust",F71)),OR(O71="warehouse_lost",O71="warehouse_damaged",O71="carrier_damaged",O71="transit_lost")),"yes","no") | Q71: =IF(P71="yes",IF(N71<>"",N71,MAX(0,-H71)),0)
A72: 2026-07-10 | B72: X0TH0023 | C72: B0TH023KX | D72: TH-TRICOR-23 | E72: Trivet Cork Set | F72: Adjustments | G72: ADJ-77246 | H72: -8 | I72: DFW6 | J72: DAMAGED | K72: K | L72: US | M72: 8 | O72: =IFERROR(VLOOKUP(K72,'Reason codes'!$A$2:$B$40,2,FALSE),"") | P72: =IF(AND(ISNUMBER(SEARCH("adjust",F72)),OR(O72="warehouse_lost",O72="warehouse_damaged",O72="carrier_damaged",O72="transit_lost")),"yes","no") | Q72: =IF(P72="yes",IF(N72<>"",N72,MAX(0,-H72)),0)
A73: 2026-07-11 | B73: X0TH0008 | C73: B0TH008KX | D73: TH-CHEKNI-08 | E73: Chef Knife 8in | F73: Receipts | G73: FBA15TH77076 | H73: 675 | I73: LAX9 | J73: SELLABLE | L73: US | M73: 0 | N73: 0 | O73: =IFERROR(VLOOKUP(K73,'Reason codes'!$A$2:$B$40,2,FALSE),"") | P73: =IF(AND(ISNUMBER(SEARCH("adjust",F73)),OR(O73="warehouse_lost",O73="warehouse_damaged",O73="carrier_damaged",O73="transit_lost")),"yes","no") | Q73: =IF(P73="yes",IF(N73<>"",N73,MAX(0,-H73)),0)
A74: 2026-07-11 | B74: X0TH0009 | C74: B0TH009KX | D74: TH-PARKNI-09 | E74: Paring Knife 3.5in | F74: Adjustments | G74: ADJ-77088 | H74: -9 | I74: ONT8 | J74: DAMAGED | K74: H | L74: US | M74: 9 | O74: =IFERROR(VLOOKUP(K74,'Reason codes'!$A$2:$B$40,2,FALSE),"") | P74: =IF(AND(ISNUMBER(SEARCH("adjust",F74)),OR(O74="warehouse_lost",O74="warehouse_damaged",O74="carrier_damaged",O74="transit_lost")),"yes","no") | Q74: =IF(P74="yes",IF(N74<>"",N74,MAX(0,-H74)),0)
A75: 2026-07-11 | B75: X0TH0017 | C75: B0TH017KX | D75: TH-FREPRE-17 | E75: French Press 34oz | F75: Adjustments | G75: ADJ-77179 | H75: -16 | I75: DFW6 | J75: SELLABLE | K75: M | L75: US | M75: 0 | N75: 16 | O75: =IFERROR(VLOOKUP(K75,'Reason codes'!$A$2:$B$40,2,FALSE),"") | P75: =IF(AND(ISNUMBER(SEARCH("adjust",F75)),OR(O75="warehouse_lost",O75="warehouse_damaged",O75="carrier_damaged",O75="transit_lost")),"yes","no") | Q75: =IF(P75="yes",IF(N75<>"",N75,MAX(0,-H75)),0)
A76: 2026-07-11 | B76: X0TH0018 | C76: B0TH018KX | D76: TH-POUOVE-18 | E76: Pour Over Kettle Gooseneck | F76: Adjustments | G76: ADJ-77191 | H76: -4 | I76: PHX7 | J76: SELLABLE | K76: 6 | L76: US | M76: 4 | O76: =IFERROR(VLOOKUP(K76,'Reason codes'!$A$2:$B$40,2,FALSE),"") | P76: =IF(AND(ISNUMBER(SEARCH("adjust",F76)),OR(O76="warehouse_lost",O76="warehouse_damaged",O76="carrier_damaged",O76="transit_lost")),"yes","no") | Q76: =IF(P76="yes",IF(N76<>"",N76,MAX(0,-H76)),0)
A77: 2026-07-11 | B77: X0TH0019 | C77: B0TH019KX | D77: TH-COFCAN-19 | E77: Coffee Canister Airtight | F77: Adjustments | G77: ADJ-77198 | H77: -17 | I77: LAX9 | J77: SELLABLE | K77: M | L77: US | M77: 0 | N77: 17 | O77: =IFERROR(VLOOKUP(K77,'Reason codes'!$A$2:$B$40,2,FALSE),"") | P77: =IF(AND(ISNUMBER(SEARCH("adjust",F77)),OR(O77="warehouse_lost",O77="warehouse_damaged",O77="carrier_damaged",O77="transit_lost")),"yes","no") | Q77: =IF(P77="yes",IF(N77<>"",N77,MAX(0,-H77)),0)
A78: 2026-07-11 | B78: X0TH0023 | C78: B0TH023KX | D78: TH-TRICOR-23 | E78: Trivet Cork Set | F78: Adjustments | G78: ADJ-77244 | H78: -8 | I78: MDW2 | J78: SELLABLE | K78: M | L78: US | M78: 8 | O78: =IFERROR(VLOOKUP(K78,'Reason codes'!$A$2:$B$40,2,FALSE),"") | P78: =IF(AND(ISNUMBER(SEARCH("adjust",F78)),OR(O78="warehouse_lost",O78="warehouse_damaged",O78="carrier_damaged",O78="transit_lost")),"yes","no") | Q78: =IF(P78="yes",IF(N78<>"",N78,MAX(0,-H78)),0)
A79: 2026-07-11 | B79: X0TH0024 | C79: B0TH024KX | D79: TH-KITTOW-24 | E79: Kitchen Towels Linen 4pk | F79: Adjustments | G79: ADJ-77255 | H79: -9 | I79: LAX9 | J79: SELLABLE | K79: 6 | L79: US | M79: 9 | O79: =IFERROR(VLOOKUP(K79,'Reason codes'!$A$2:$B$40,2,FALSE),"") | P79: =IF(AND(ISNUMBER(SEARCH("adjust",F79)),OR(O79="warehouse_lost",O79="warehouse_damaged",O79="carrier_damaged",O79="transit_lost")),"yes","no") | Q79: =IF(P79="yes",IF(N79<>"",N79,MAX(0,-H79)),0)
A80: 2026-07-12 | B80: X0TH0002 | C80: B0TH002KX | D80: TH-CASIRO-02 | E80: Cast Iron Skillet 12in | F80: Adjustments | G80: ADJ-77013 | H80: -13 | I80: DFW6 | J80: SELLABLE | K80: 6 | L80: US | M80: 13 | O80: =IFERROR(VLOOKUP(K80,'Reason codes'!$A$2:$B$40,2,FALSE),"") | P80: =IF(AND(ISNUMBER(SEARCH("adjust",F80)),OR(O80="warehouse_lost",O80="warehouse_damaged",O80="carrier_damaged",O80="transit_lost")),"yes","no") | Q80: =IF(P80="yes",IF(N80<>"",N80,MAX(0,-H80)),0)
A81: 2026-07-13 | B81: X0TH0009 | C81: B0TH009KX | D81: TH-PARKNI-09 | E81: Paring Knife 3.5in | F81: Adjustments | G81: ADJ-77087 | H81: -25 | I81: MDW2 | J81: SELLABLE | K81: M | L81: US | M81: 0 | N81: 25 | O81: =IFERROR(VLOOKUP(K81,'Reason codes'!$A$2:$B$40,2,FALSE),"") | P81: =IF(AND(ISNUMBER(SEARCH("adjust",F81)),OR(O81="warehouse_lost",O81="warehouse_damaged",O81="carrier_damaged",O81="transit_lost")),"yes","no") | Q81: =IF(P81="yes",IF(N81<>"",N81,MAX(0,-H81)),0)
A82: 2026-07-13 | B82: X0TH0022 | C82: B0TH022KX | D82: TH-OVEMIT-22 | E82: Oven Mitts Aramid Pair | F82: Receipts | G82: FBA15TH77231 | H82: 780 | I82: DFW6 | J82: SELLABLE | L82: US | M82: 0 | N82: 0 | O82: =IFERROR(VLOOKUP(K82,'Reason codes'!$A$2:$B$40,2,FALSE),"") | P82: =IF(AND(ISNUMBER(SEARCH("adjust",F82)),OR(O82="warehouse_lost",O82="warehouse_damaged",O82="carrier_damaged",O82="transit_lost")),"yes","no") | Q82: =IF(P82="yes",IF(N82<>"",N82,MAX(0,-H82)),0)
A83: 2026-07-14 | B83: X0TH0006 | C83: B0TH006KX | D83: TH-BAMCUT-06 | E83: Bamboo Cutting Board M | F83: Receipts | G83: FBA15TH77054 | H83: 1080 | I83: PHX7 | J83: SELLABLE | L83: US | M83: 0 | N83: 0 | O83: =IFERROR(VLOOKUP(K83,'Reason codes'!$A$2:$B$40,2,FALSE),"") | P83: =IF(AND(ISNUMBER(SEARCH("adjust",F83)),OR(O83="warehouse_lost",O83="warehouse_damaged",O83="carrier_damaged",O83="transit_lost")),"yes","no") | Q83: =IF(P83="yes",IF(N83<>"",N83,MAX(0,-H83)),0)
A84: 2026-07-14 | B84: X0TH0008 | C84: B0TH008KX | D84: TH-CHEKNI-08 | E84: Chef Knife 8in | F84: Adjustments | G84: ADJ-77077 | H84: -7 | I84: ONT8 | J84: SELLABLE | K84: M | L84: US | M84: 0 | N84: 7 | O84: =IFERROR(VLOOKUP(K84,'Reason codes'!$A$2:$B$40,2,FALSE),"") | P84: =IF(AND(ISNUMBER(SEARCH("adjust",F84)),OR(O84="warehouse_lost",O84="warehouse_damaged",O84="carrier_damaged",O84="transit_lost")),"yes","no") | Q84: =IF(P84="yes",IF(N84<>"",N84,MAX(0,-H84)),0)
A85: 2026-07-14 | B85: X0TH0020 | C85: B0TH020KX | D85: TH-TEAINF-20 | E85: Tea Infuser Mug | F85: Adjustments | G85: ADJ-77210 | H85: -14 | I85: LAX9 | J85: SELLABLE | K85: M | L85: US | M85: 14 | O85: =IFERROR(VLOOKUP(K85,'Reason codes'!$A$2:$B$40,2,FALSE),"") | P85: =IF(AND(ISNUMBER(SEARCH("adjust",F85)),OR(O85="warehouse_lost",O85="warehouse_damaged",O85="carrier_damaged",O85="transit_lost")),"yes","no") | Q85: =IF(P85="yes",IF(N85<>"",N85,MAX(0,-H85)),0)
A86: 2026-07-15 | B86: X0TH0014 | C86: B0TH014KX | D86: TH-MEACUP-14 | E86: Measuring Cups Steel | F86: Adjustments | G86: ADJ-77147 | H86: -10 | I86: ONT8 | J86: SELLABLE | K86: M | L86: US | M86: 10 | O86: =IFERROR(VLOOKUP(K86,'Reason codes'!$A$2:$B$40,2,FALSE),"") | P86: =IF(AND(ISNUMBER(SEARCH("adjust",F86)),OR(O86="warehouse_lost",O86="warehouse_damaged",O86="carrier_damaged",O86="transit_lost")),"yes","no") | Q86: =IF(P86="yes",IF(N86<>"",N86,MAX(0,-H86)),0)
A87: 2026-07-15 | B87: X0TH0024 | C87: B0TH024KX | D87: TH-KITTOW-24 | E87: Kitchen Towels Linen 4pk | F87: Adjustments | G87: ADJ-77253 | H87: -20 | I87: DFW6 | J87: SELLABLE | K87: M | L87: US | M87: 20 | O87: =IFERROR(VLOOKUP(K87,'Reason codes'!$A$2:$B$40,2,FALSE),"") | P87: =IF(AND(ISNUMBER(SEARCH("adjust",F87)),OR(O87="warehouse_lost",O87="warehouse_damaged",O87="carrier_damaged",O87="transit_lost")),"yes","no") | Q87: =IF(P87="yes",IF(N87<>"",N87,MAX(0,-H87)),0)
A88: 2026-07-18 | B88: X0TH0006 | C88: B0TH006KX | D88: TH-BAMCUT-06 | E88: Bamboo Cutting Board M | F88: Adjustments | G88: ADJ-77056 | H88: -15 | I88: ONT8 | J88: SELLABLE | K88: M | L88: US | M88: 0 | N88: 15 | O88: =IFERROR(VLOOKUP(K88,'Reason codes'!$A$2:$B$40,2,FALSE),"") | P88: =IF(AND(ISNUMBER(SEARCH("adjust",F88)),OR(O88="warehouse_lost",O88="warehouse_damaged",O88="carrier_damaged",O88="transit_lost")),"yes","no") | Q88: =IF(P88="yes",IF(N88<>"",N88,MAX(0,-H88)),0)
A89: 2026-07-19 | B89: X0TH0013 | C89: B0TH013KX | D89: TH-SILSPA-13 | E89: Silicone Spatula Set | F89: Receipts | G89: FBA15TH77136 | H89: 1350 | I89: ONT8 | J89: SELLABLE | L89: US | M89: 0 | N89: 0 | O89: =IFERROR(VLOOKUP(K89,'Reason codes'!$A$2:$B$40,2,FALSE),"") | P89: =IF(AND(ISNUMBER(SEARCH("adjust",F89)),OR(O89="warehouse_lost",O89="warehouse_damaged",O89="carrier_damaged",O89="transit_lost")),"yes","no") | Q89: =IF(P89="yes",IF(N89<>"",N89,MAX(0,-H89)),0)
A90: 2026-07-20 | B90: X0TH0010 | C90: B0TH010KX | D90: TH-BREKNI-10 | E90: Bread Knife 10in | F90: Adjustments | G90: ADJ-77100 | H90: -1 | I90: PHX7 | J90: CUSTOMER_DAMAGED | K90: E | L90: US | M90: 1 | N90: 0 | O90: =IFERROR(VLOOKUP(K90,'Reason codes'!$A$2:$B$40,2,FALSE),"") | P90: =IF(AND(ISNUMBER(SEARCH("adjust",F90)),OR(O90="warehouse_lost",O90="warehouse_damaged",O90="carrier_damaged",O90="transit_lost")),"yes","no") | Q90: =IF(P90="yes",IF(N90<>"",N90,MAX(0,-H90)),0)
A91: 2026-07-20 | B91: X0TH0011 | C91: B0TH011KX | D91: TH-KNISHA-11 | E91: Knife Sharpener Whetstone | F91: Adjustments | G91: ADJ-77110 | H91: -4 | I91: PHX7 | J91: SELLABLE | K91: M | L91: US | M91: 4 | O91: =IFERROR(VLOOKUP(K91,'Reason codes'!$A$2:$B$40,2,FALSE),"") | P91: =IF(AND(ISNUMBER(SEARCH("adjust",F91)),OR(O91="warehouse_lost",O91="warehouse_damaged",O91="carrier_damaged",O91="transit_lost")),"yes","no") | Q91: =IF(P91="yes",IF(N91<>"",N91,MAX(0,-H91)),0)
A92: 2026-07-21 | B92: X0TH0009 | C92: B0TH009KX | D92: TH-PARKNI-09 | E92: Paring Knife 3.5in | F92: Receipts | G92: FBA15TH77085 | H92: 915 | I92: PHX7 | J92: SELLABLE | L92: US | M92: 0 | N92: 0 | O92: =IFERROR(VLOOKUP(K92,'Reason codes'!$A$2:$B$40,2,FALSE),"") | P92: =IF(AND(ISNUMBER(SEARCH("adjust",F92)),OR(O92="warehouse_lost",O92="warehouse_damaged",O92="carrier_damaged",O92="transit_lost")),"yes","no") | Q92: =IF(P92="yes",IF(N92<>"",N92,MAX(0,-H92)),0)
A93: 2026-07-22 | B93: X0TH0017 | C93: B0TH017KX | D93: TH-FREPRE-17 | E93: French Press 34oz | F93: Adjustments | G93: ADJ-77180 | H93: 9 | I93: MDW2 | J93: SELLABLE | K93: F | L93: US | M93: 1 | N93: 0 | O93: =IFERROR(VLOOKUP(K93,'Reason codes'!$A$2:$B$40,2,FALSE),"") | P93: =IF(AND(ISNUMBER(SEARCH("adjust",F93)),OR(O93="warehouse_lost",O93="warehouse_damaged",O93="carrier_damaged",O93="transit_lost")),"yes","no") | Q93: =IF(P93="yes",IF(N93<>"",N93,MAX(0,-H93)),0)
A94: 2026-07-23 | B94: X0TH0007 | C94: B0TH007KX | D94: TH-WALSER-07 | E94: Walnut Serving Tray | F94: Adjustments | G94: ADJ-77067 | H94: -7 | I94: PHX7 | J94: SELLABLE | K94: M | L94: US | M94: 0 | N94: 7 | O94: =IFERROR(VLOOKUP(K94,'Reason codes'!$A$2:$B$40,2,FALSE),"") | P94: =IF(AND(ISNUMBER(SEARCH("adjust",F94)),OR(O94="warehouse_lost",O94="warehouse_damaged",O94="carrier_damaged",O94="transit_lost")),"yes","no") | Q94: =IF(P94="yes",IF(N94<>"",N94,MAX(0,-H94)),0)
A95: 2026-07-24 | B95: X0TH0016 | C95: B0TH016KX | D95: TH-PEPMIL-16 | E95: Pepper Mill Walnut | F95: Adjustments | G95: ADJ-77170 | H95: -18 | I95: ONT8 | J95: SELLABLE | K95: M | L95: US | M95: 0 | N95: 18 | O95: =IFERROR(VLOOKUP(K95,'Reason codes'!$A$2:$B$40,2,FALSE),"") | P95: =IF(AND(ISNUMBER(SEARCH("adjust",F95)),OR(O95="warehouse_lost",O95="warehouse_damaged",O95="carrier_damaged",O95="transit_lost")),"yes","no") | Q95: =IF(P95="yes",IF(N95<>"",N95,MAX(0,-H95)),0)
A96: 2026-07-24 | B96: X0TH0018 | C96: B0TH018KX | D96: TH-POUOVE-18 | E96: Pour Over Kettle Gooseneck | F96: Adjustments | G96: ADJ-77189 | H96: -18 | I96: ONT8 | J96: SELLABLE | K96: M | L96: US | M96: 0 | N96: 18 | O96: =IFERROR(VLOOKUP(K96,'Reason codes'!$A$2:$B$40,2,FALSE),"") | P96: =IF(AND(ISNUMBER(SEARCH("adjust",F96)),OR(O96="warehouse_lost",O96="warehouse_damaged",O96="carrier_damaged",O96="transit_lost")),"yes","no") | Q96: =IF(P96="yes",IF(N96<>"",N96,MAX(0,-H96)),0)
A97: 2026-07-27 | B97: X0TH0003 | C97: B0TH003KX | D97: TH-ENADUT-03 | E97: Enamel Dutch Oven 5qt | F97: Adjustments | G97: ADJ-77026 | H97: -8 | I97: MDW2 | J97: SELLABLE | K97: M | L97: US | M97: 8 | O97: =IFERROR(VLOOKUP(K97,'Reason codes'!$A$2:$B$40,2,FALSE),"") | P97: =IF(AND(ISNUMBER(SEARCH("adjust",F97)),OR(O97="warehouse_lost",O97="warehouse_damaged",O97="carrier_damaged",O97="transit_lost")),"yes","no") | Q97: =IF(P97="yes",IF(N97<>"",N97,MAX(0,-H97)),0)
A98: 2026-07-27 | B98: X0TH0004 | C98: B0TH004KX | D98: TH-CARSTE-04 | E98: Carbon Steel Wok | F98: Adjustments | G98: ADJ-77036 | H98: -18 | I98: LAX9 | J98: SELLABLE | K98: M | L98: US | M98: 0 | N98: 18 | O98: =IFERROR(VLOOKUP(K98,'Reason codes'!$A$2:$B$40,2,FALSE),"") | P98: =IF(AND(ISNUMBER(SEARCH("adjust",F98)),OR(O98="warehouse_lost",O98="warehouse_damaged",O98="carrier_damaged",O98="transit_lost")),"yes","no") | Q98: =IF(P98="yes",IF(N98<>"",N98,MAX(0,-H98)),0)
A99: 2026-07-27 | B99: X0TH0019 | C99: B0TH019KX | D99: TH-COFCAN-19 | E99: Coffee Canister Airtight | F99: Adjustments | G99: ADJ-77199 | H99: 7 | I99: DFW6 | J99: SELLABLE | K99: F | L99: US | M99: 1 | N99: 0 | O99: =IFERROR(VLOOKUP(K99,'Reason codes'!$A$2:$B$40,2,FALSE),"") | P99: =IF(AND(ISNUMBER(SEARCH("adjust",F99)),OR(O99="warehouse_lost",O99="warehouse_damaged",O99="carrier_damaged",O99="transit_lost")),"yes","no") | Q99: =IF(P99="yes",IF(N99<>"",N99,MAX(0,-H99)),0)
A100: 2026-07-28 | B100: X0TH0015 | C100: B0TH015KX | D100: TH-SALCEL-15 | E100: Salt Cellar Acacia | F100: Adjustments | G100: ADJ-77161 | H100: -20 | I100: LAX9 | J100: SELLABLE | K100: M | L100: US | M100: 20 | O100: =IFERROR(VLOOKUP(K100,'Reason codes'!$A$2:$B$40,2,FALSE),"") | P100: =IF(AND(ISNUMBER(SEARCH("adjust",F100)),OR(O100="warehouse_lost",O100="warehouse_damaged",O100="carrier_damaged",O100="transit_lost")),"yes","no") | Q100: =IF(P100="yes",IF(N100<>"",N100,MAX(0,-H100)),0)
A101: 2026-07-29 | B101: X0TH0014 | C101: B0TH014KX | D101: TH-MEACUP-14 | E101: Measuring Cups Steel | F101: Adjustments | G101: ADJ-77151 | H101: -1 | I101: DFW6 | J101: CUSTOMER_DAMAGED | K101: E | L101: US | M101: 1 | N101: 0 | O101: =IFERROR(VLOOKUP(K101,'Reason codes'!$A$2:$B$40,2,FALSE),"") | P101: =IF(AND(ISNUMBER(SEARCH("adjust",F101)),OR(O101="warehouse_lost",O101="warehouse_damaged",O101="carrier_damaged",O101="transit_lost")),"yes","no") | Q101: =IF(P101="yes",IF(N101<>"",N101,MAX(0,-H101)),0)
A102: 2026-08-04 | B102: X0TH0015 | C102: B0TH015KX | D102: TH-SALCEL-15 | E102: Salt Cellar Acacia | F102: Receipts | G102: FBA15TH77159 | H102: 525 | I102: DFW6 | J102: SELLABLE | L102: US | M102: 0 | N102: 0 | O102: =IFERROR(VLOOKUP(K102,'Reason codes'!$A$2:$B$40,2,FALSE),"") | P102: =IF(AND(ISNUMBER(SEARCH("adjust",F102)),OR(O102="warehouse_lost",O102="warehouse_damaged",O102="carrier_damaged",O102="transit_lost")),"yes","no") | Q102: =IF(P102="yes",IF(N102<>"",N102,MAX(0,-H102)),0)
A103: 2026-08-04 | B103: X0TH0017 | C103: B0TH017KX | D103: TH-FREPRE-17 | E103: French Press 34oz | F103: Adjustments | G103: ADJ-77182 | H103: -1 | I103: MDW2 | J103: CUSTOMER_DAMAGED | K103: E | L103: US | M103: 1 | N103: 0 | O103: =IFERROR(VLOOKUP(K103,'Reason codes'!$A$2:$B$40,2,FALSE),"") | P103: =IF(AND(ISNUMBER(SEARCH("adjust",F103)),OR(O103="warehouse_lost",O103="warehouse_damaged",O103="carrier_damaged",O103="transit_lost")),"yes","no") | Q103: =IF(P103="yes",IF(N103<>"",N103,MAX(0,-H103)),0)
A104: 2026-08-05 | B104: X0TH0004 | C104: B0TH004KX | D104: TH-CARSTE-04 | E104: Carbon Steel Wok | F104: Adjustments | G104: ADJ-77040 | H104: -1 | I104: MDW2 | J104: CUSTOMER_DAMAGED | K104: E | L104: US | M104: 1 | N104: 0 | O104: =IFERROR(VLOOKUP(K104,'Reason codes'!$A$2:$B$40,2,FALSE),"") | P104: =IF(AND(ISNUMBER(SEARCH("adjust",F104)),OR(O104="warehouse_lost",O104="warehouse_damaged",O104="carrier_damaged",O104="transit_lost")),"yes","no") | Q104: =IF(P104="yes",IF(N104<>"",N104,MAX(0,-H104)),0)
A105: 2026-08-05 | B105: X0TH0006 | C105: B0TH006KX | D105: TH-BAMCUT-06 | E105: Bamboo Cutting Board M | F105: Adjustments | G105: ADJ-77057 | H105: -4 | I105: MDW2 | J105: DAMAGED | K105: D | L105: US | M105: 0 | N105: 4 | O105: =IFERROR(VLOOKUP(K105,'Reason codes'!$A$2:$B$40,2,FALSE),"") | P105: =IF(AND(ISNUMBER(SEARCH("adjust",F105)),OR(O105="warehouse_lost",O105="warehouse_damaged",O105="carrier_damaged",O105="transit_lost")),"yes","no") | Q105: =IF(P105="yes",IF(N105<>"",N105,MAX(0,-H105)),0)
A106: 2026-08-06 | B106: X0TH0022 | C106: B0TH022KX | D106: TH-OVEMIT-22 | E106: Oven Mitts Aramid Pair | F106: Adjustments | G106: ADJ-77233 | H106: -8 | I106: ONT8 | J106: DAMAGED | K106: Q | L106: US | M106: 8 | O106: =IFERROR(VLOOKUP(K106,'Reason codes'!$A$2:$B$40,2,FALSE),"") | P106: =IF(AND(ISNUMBER(SEARCH("adjust",F106)),OR(O106="warehouse_lost",O106="warehouse_damaged",O106="carrier_damaged",O106="transit_lost")),"yes","no") | Q106: =IF(P106="yes",IF(N106<>"",N106,MAX(0,-H106)),0)
A107: 2026-08-07 | B107: X0TH0011 | C107: B0TH011KX | D107: TH-KNISHA-11 | E107: Knife Sharpener Whetstone | F107: Receipts | G107: FBA15TH77109 | H107: 570 | I107: DFW6 | J107: SELLABLE | L107: US | M107: 0 | N107: 0 | O107: =IFERROR(VLOOKUP(K107,'Reason codes'!$A$2:$B$40,2,FALSE),"") | P107: =IF(AND(ISNUMBER(SEARCH("adjust",F107)),OR(O107="warehouse_lost",O107="warehouse_damaged",O107="carrier_damaged",O107="transit_lost")),"yes","no") | Q107: =IF(P107="yes",IF(N107<>"",N107,MAX(0,-H107)),0)
A108: 2026-08-07 | B108: X0TH0012 | C108: B0TH012KX | D108: TH-STAMIX-12 | E108: Stainless Mixing Bowls 5pc | F108: Adjustments | G108: ADJ-77126 | H108: -4 | I108: MDW2 | J108: DAMAGED | K108: D | L108: US | M108: 0 | N108: 4 | O108: =IFERROR(VLOOKUP(K108,'Reason codes'!$A$2:$B$40,2,FALSE),"") | P108: =IF(AND(ISNUMBER(SEARCH("adjust",F108)),OR(O108="warehouse_lost",O108="warehouse_damaged",O108="carrier_damaged",O108="transit_lost")),"yes","no") | Q108: =IF(P108="yes",IF(N108<>"",N108,MAX(0,-H108)),0)
A109: 2026-08-08 | B109: X0TH0002 | C109: B0TH002KX | D109: TH-CASIRO-02 | E109: Cast Iron Skillet 12in | F109: Receipts | G109: FBA15TH77011 | H109: 615 | I109: DFW6 | J109: SELLABLE | L109: US | M109: 0 | N109: 0 | O109: =IFERROR(VLOOKUP(K109,'Reason codes'!$A$2:$B$40,2,FALSE),"") | P109: =IF(AND(ISNUMBER(SEARCH("adjust",F109)),OR(O109="warehouse_lost",O109="warehouse_damaged",O109="carrier_damaged",O109="transit_lost")),"yes","no") | Q109: =IF(P109="yes",IF(N109<>"",N109,MAX(0,-H109)),0)
A110: 2026-08-09 | B110: X0TH0004 | C110: B0TH004KX | D110: TH-CARSTE-04 | E110: Carbon Steel Wok | F110: Adjustments | G110: ADJ-77037 | H110: -2 | I110: MDW2 | J110: DAMAGED | K110: D | L110: US | M110: 0 | N110: 2 | O110: =IFERROR(VLOOKUP(K110,'Reason codes'!$A$2:$B$40,2,FALSE),"") | P110: =IF(AND(ISNUMBER(SEARCH("adjust",F110)),OR(O110="warehouse_lost",O110="warehouse_damaged",O110="carrier_damaged",O110="transit_lost")),"yes","no") | Q110: =IF(P110="yes",IF(N110<>"",N110,MAX(0,-H110)),0)
A111: 2026-08-09 | B111: X0TH0013 | C111: B0TH013KX | D111: TH-SILSPA-13 | E111: Silicone Spatula Set | F111: Adjustments | G111: ADJ-77138 | H111: -1 | I111: MDW2 | J111: CUSTOMER_DAMAGED | K111: E | L111: US | M111: 1 | N111: 0 | O111: =IFERROR(VLOOKUP(K111,'Reason codes'!$A$2:$B$40,2,FALSE),"") | P111: =IF(AND(ISNUMBER(SEARCH("adjust",F111)),OR(O111="warehouse_lost",O111="warehouse_damaged",O111="carrier_damaged",O111="transit_lost")),"yes","no") | Q111: =IF(P111="yes",IF(N111<>"",N111,MAX(0,-H111)),0)
A112: 2026-08-09 | B112: X0TH0021 | C112: B0TH021KX | D112: TH-APRWAX-21 | E112: Apron Waxed Canvas | F112: Adjustments | G112: ADJ-77223 | H112: -5 | I112: ONT8 | J112: DAMAGED | K112: D | L112: US | M112: 5 | O112: =IFERROR(VLOOKUP(K112,'Reason codes'!$A$2:$B$40,2,FALSE),"") | P112: =IF(AND(ISNUMBER(SEARCH("adjust",F112)),OR(O112="warehouse_lost",O112="warehouse_damaged",O112="carrier_damaged",O112="transit_lost")),"yes","no") | Q112: =IF(P112="yes",IF(N112<>"",N112,MAX(0,-H112)),0)
A113: 2026-08-10 | B113: X0TH0020 | C113: B0TH020KX | D113: TH-TEAINF-20 | E113: Tea Infuser Mug | F113: Adjustments | G113: ADJ-77211 | H113: -6 | I113: MDW2 | J113: DAMAGED | K113: Q | L113: US | M113: 0 | N113: 6 | O113: =IFERROR(VLOOKUP(K113,'Reason codes'!$A$2:$B$40,2,FALSE),"") | P113: =IF(AND(ISNUMBER(SEARCH("adjust",F113)),OR(O113="warehouse_lost",O113="warehouse_damaged",O113="carrier_damaged",O113="transit_lost")),"yes","no") | Q113: =IF(P113="yes",IF(N113<>"",N113,MAX(0,-H113)),0)
...

Sheet Returns
A1: return-date | B1: order-id | C1: sku | D1: asin | E1: fnsku | F1: product-name | G1: quantity | H1: fulfillment-center-id | I1: detailed-disposition | J1: reason | K1: status | L1: Claimable (helper)
A2: 2026-05-25 | B2: 111-4000215-7071290 | C2: TH-CASIRO-01 | D2: B0TH001KX | E2: X0TH0001 | F2: Cast Iron Skillet 10in | G2: 1 | H2: ONT8 | I2: DAMAGED | J2: ORDERED_WRONG_ITEM | K2: Unit not returned to inventory | L2: =IF(AND(OR(I2="DAMAGED",I2="CARRIER_DAMAGED"),ISERROR(SEARCH("reimburs",K2))),"yes","no")
A3: 2026-05-26 | B3: 111-4006547-6808666 | C3: TH-SILSPA-13 | D3: B0TH013KX | E3: X0TH0013 | F3: Silicone Spatula Set | G3: 1 | H3: MDW2 | I3: SELLABLE | J3: NOT_AS_DESCRIBED | K3: Unit returned to inventory | L3: =IF(AND(OR(I3="DAMAGED",I3="CARRIER_DAMAGED"),ISERROR(SEARCH("reimburs",K3))),"yes","no")
A4: 2026-05-27 | B4: 111-4007866-6847779 | C4: TH-PEPMIL-16 | D4: B0TH016KX | E4: X0TH0016 | F4: Pepper Mill Walnut | G4: 1 | H4: MDW2 | I4: CUSTOMER_DAMAGED | J4: NOT_AS_DESCRIBED | K4: Unit not returned to inventory | L4: =IF(AND(OR(I4="DAMAGED",I4="CARRIER_DAMAGED"),ISERROR(SEARCH("reimburs",K4))),"yes","no")
A5: 2026-05-28 | B5: 111-4001074-3177903 | C5: TH-CASIRO-02 | D5: B0TH002KX | E5: X0TH0002 | F5: Cast Iron Skillet 12in | G5: 1 | H5: DFW6 | I5: CARRIER_DAMAGED | J5: ORDERED_WRONG_ITEM | K5: Unit not returned to inventory | L5: =IF(AND(OR(I5="DAMAGED",I5="CARRIER_DAMAGED"),ISERROR(SEARCH("reimburs",K5))),"yes","no")
A6: 2026-05-28 | B6: 111-4006090-3906751 | C6: TH-STAMIX-12 | D6: B0TH012KX | E6: X0TH0012 | F6: Stainless Mixing Bowls 5pc | G6: 1 | H6: ONT8 | I6: DEFECTIVE | J6: NOT_AS_DESCRIBED | K6: Unit not returned to inventory | L6: =IF(AND(OR(I6="DAMAGED",I6="CARRIER_DAMAGED"),ISERROR(SEARCH("reimburs",K6))),"yes","no")
A7: 2026-05-28 | B7: 111-4011691-1549916 | C7: TH-KITTOW-24 | D7: B0TH024KX | E7: X0TH0024 | F7: Kitchen Towels Linen 4pk | G7: 1 | H7: PHX7 | I7: DAMAGED | J7: UNWANTED_ITEM | K7: Unit not returned to inventory | L7: =IF(AND(OR(I7="DAMAGED",I7="CARRIER_DAMAGED"),ISERROR(SEARCH("reimburs",K7))),"yes","no")
A8: 2026-05-29 | B8: 111-4000397-3921245 | C8: TH-CASIRO-01 | D8: B0TH001KX | E8: X0TH0001 | F8: Cast Iron Skillet 10in | G8: 1 | H8: PHX7 | I8: SELLABLE | J8: DEFECTIVE | K8: Unit returned to inventory | L8: =IF(AND(OR(I8="DAMAGED",I8="CARRIER_DAMAGED"),ISERROR(SEARCH("reimburs",K8))),"yes","no")
A9: 2026-05-30 | B9: 111-4000290-1596218 | C9: TH-CASIRO-01 | D9: B0TH001KX | E9: X0TH0001 | F9: Cast Iron Skillet 10in | G9: 1 | H9: MDW2 | I9: DEFECTIVE | J9: UNWANTED_ITEM | K9: Unit not returned to inventory | L9: =IF(AND(OR(I9="DAMAGED",I9="CARRIER_DAMAGED"),ISERROR(SEARCH("reimburs",K9))),"yes","no")
A10: 2026-05-31 | B10: 111-4000484-5296207 | C10: TH-CASIRO-01 | D10: B0TH001KX | E10: X0TH0001 | F10: Cast Iron Skillet 10in | G10: 1 | H10: MDW2 | I10: DAMAGED | J10: UNWANTED_ITEM | K10: Unit not returned to inventory | L10: =IF(AND(OR(I10="DAMAGED",I10="CARRIER_DAMAGED"),ISERROR(SEARCH("reimburs",K10))),"yes","no")
A11: 2026-05-31 | B11: 111-4004114-9710250 | C11: TH-PARKNI-09 | D11: B0TH009KX | E11: X0TH0009 | F11: Paring Knife 3.5in | G11: 1 | H11: MDW2 | I11: SELLABLE | J11: UNWANTED_ITEM | K11: Unit returned to inventory | L11: =IF(AND(OR(I11="DAMAGED",I11="CARRIER_DAMAGED"),ISERROR(SEARCH("reimburs",K11))),"yes","no")
A12: 2026-05-31 | B12: 111-4005020-9298239 | C12: TH-KNISHA-11 | D12: B0TH011KX | E12: X0TH0011 | F12: Knife Sharpener Whetstone | G12: 1 | H12: ONT8 | I12: SELLABLE | J12: UNWANTED_ITEM | K12: Unit returned to inventory | L12: =IF(AND(OR(I12="DAMAGED",I12="CARRIER_DAMAGED"),ISERROR(SEARCH("reimburs",K12))),"yes","no")
A13: 2026-05-31 | B13: 111-4006766-2952585 | C13: TH-MEACUP-14 | D13: B0TH014KX | E13: X0TH0014 | F13: Measuring Cups Steel | G13: 1 | H13: LAX9 | I13: SELLABLE | J13: NOT_AS_DESCRIBED | K13: Unit returned to inventory | L13: =IF(AND(OR(I13="DAMAGED",I13="CARRIER_DAMAGED"),ISERROR(SEARCH("reimburs",K13))),"yes","no")
... A125: 2026-08-29 | B125: 111-4009157-6843329 | C125: TH-COFCAN-19 | D125: B0TH019KX | E125: X0TH0019 | F125: Coffee Canister Airtight | G125: 1 | H125: PHX7 | I125: DAMAGED | J125: ORDERED_WRONG_ITEM | K125: Unit not returned to inventory | L125: =IF(AND(OR(I125="DAMAGED",I125="CARRIER_DAMAGED"),ISERROR(SEARCH("reimburs",K125))),"yes","no")

Sheet Reimbursements
A1: approval-date | B1: reimbursement-id | C1: case-id | D1: amazon-order-id | E1: reason | F1: sku | G1: fnsku | H1: asin | I1: amount-per-unit | J1: amount-total | K1: quantity-reimbursed-cash | L1: quantity-reimbursed-inventory | M1: quantity-reimbursed-total | N1: original-reimbursement-type | O1: Cash share (helper)
A2: 2026-06-14 | B2: RM-77074 | E2: Damaged_Warehouse | F2: TH-WALSER-07 | G2: X0TH0007 | H2: B0TH007KX | I2: 13.1 | J2: 26.2 | K2: 2 | L2: 0 | M2: 2 | O2: =IF(M2>0,IF(K2<>"",K2,M2)/M2,0)
A3: 2026-06-24 | B3: RM-77084 | E3: Lost_Warehouse | F3: TH-CHEKNI-08 | G3: X0TH0008 | H3: B0TH008KX | I3: 16.6 | J3: 49.8 | K3: 3 | L3: 0 | M3: 3 | O3: =IF(M3>0,IF(K3<>"",K3,M3)/M3,0)
A4: 2026-06-30 | B4: RM-77064 | E4: Damaged_Warehouse | F4: TH-BAMCUT-06 | G4: X0TH0006 | H4: B0TH006KX | I4: 5.5 | J4: 0 | K4: 0 | L4: 3 | M4: 3 | O4: =IF(M4>0,IF(K4<>"",K4,M4)/M4,0)
A5: 2026-06-30 | B5: RM-77250 | E5: Damaged_Warehouse | F5: TH-TRICOR-23 | G5: X0TH0023 | H5: B0TH023KX | I5: 2.6 | J5: 7.8 | K5: 3 | L5: 0 | M5: 3 | O5: =IF(M5>0,IF(K5<>"",K5,M5)/M5,0)
A6: 2026-07-05 | B6: RM-77095 | E6: Lost_Warehouse | F6: TH-PARKNI-09 | G6: X0TH0009 | H6: B0TH009KX | I6: 4.8 | J6: 14.4 | K6: 3 | L6: 0 | M6: 3 | O6: =IF(M6>0,IF(K6<>"",K6,M6)/M6,0)
A7: 2026-07-15 | B7: RM-77122 | E7: Lost_Warehouse | F7: TH-KNISHA-11 | G7: X0TH0011 | H7: B0TH011KX | I7: 6.5 | J7: 6.5 | K7: 1 | L7: 0 | M7: 1 | O7: =IF(M7>0,IF(K7<>"",K7,M7)/M7,0)
A8: 2026-07-26 | B8: RM-77186 | E8: Damaged_Warehouse | F8: TH-FREPRE-17 | G8: X0TH0017 | H8: B0TH017KX | I8: 9 | J8: 27 | K8: 3 | L8: 0 | M8: 3 | O8: =IF(M8>0,IF(K8<>"",K8,M8)/M8,0)
A9: 2026-07-27 | B9: RM-77023 | E9: Lost_Warehouse | F9: TH-CASIRO-02 | G9: X0TH0002 | H9: B0TH002KX | I9: 16.1 | J9: 32.2 | K9: 2 | L9: 0 | M9: 2 | O9: =IF(M9>0,IF(K9<>"",K9,M9)/M9,0)
A10: 2026-08-08 | B10: RM-77045 | E10: Lost_Warehouse | F10: TH-CARSTE-04 | G10: X0TH0004 | H10: B0TH004KX | I10: 16.1 | J10: 32.2 | K10: 2 | L10: 0 | M10: 2 | O10: =IF(M10>0,IF(K10<>"",K10,M10)/M10,0)
A11: 2026-08-11 | B11: RM-77144 | E11: Lost_Warehouse | F11: TH-SILSPA-13 | G11: X0TH0013 | H11: B0TH013KX | I11: 3.3 | J11: 0 | K11: 0 | L11: 3 | M11: 3 | O11: =IF(M11>0,IF(K11<>"",K11,M11)/M11,0)
A12: 2026-08-20 | B12: RM-77264 | E12: Reversal | F12: TH-CARSTE-04 | G12: X0TH0004 | H12: B0TH004KX | I12: -16.1 | J12: -32.2 | K12: 2 | L12: 0 | M12: 2 | N12: Reversal | O12: =IF(M12>0,IF(K12<>"",K12,M12)/M12,0)
A13: 2026-08-23 | B13: RM-77167 | E13: Damaged_Warehouse | F13: TH-SALCEL-15 | G13: X0TH0015 | H13: B0TH015KX | I13: 4.1 | J13: 8.2 | K13: 2 | L13: 0 | M13: 2 | O13: =IF(M13>0,IF(K13<>"",K13,M13)/M13,0)

Sheet Refunds
A1: date/time | B1: type | C1: order id | D1: sku | E1: quantity | F1: product sales | G1: total | H1: Age in days (helper) | I1: Units returned (helper) | J1: Short (helper)
A2: 2026-05-08T20:00:00 | B2: Refund | C2: 111-4001167-4531939 | D2: TH-CASIRO-02 | E2: 1 | F2: -46.34 | G2: -40.78 | H2: =IFERROR(Windows!$B$2-DATEVALUE(LEFT(A2,10)),"") | I2: =SUMIFS(Returns!$G:$G,Returns!$B:$B,C2) | J2: =MAX(0,ABS(E2)-I2)
A3: 2026-05-11T16:00:00 | B3: Refund | C3: 111-4006638-6018624 | D3: TH-SILSPA-13 | E3: 1 | F3: -15.44 | G3: -13.59 | H3: =IFERROR(Windows!$B$2-DATEVALUE(LEFT(A3,10)),"") | I3: =SUMIFS(Returns!$G:$G,Returns!$B:$B,C3) | J3: =MAX(0,ABS(E3)-I3)
A4: 2026-05-12T14:00:00 | B4: Refund | C4: 111-4004228-2926992 | D4: TH-PARKNI-09 | E4: 1 | F4: -18.42 | G4: -16.21 | H4: =IFERROR(Windows!$B$2-DATEVALUE(LEFT(A4,10)),"") | I4: =SUMIFS(Returns!$G:$G,Returns!$B:$B,C4) | J4: =MAX(0,ABS(E4)-I4)
A5: 2026-05-15T01:00:00 | B5: Refund | C5: 111-4008814-6418098 | D5: TH-POUOVE-18 | E5: 1 | F5: -44.28 | G5: -38.97 | H5: =IFERROR(Windows!$B$2-DATEVALUE(LEFT(A5,10)),"") | I5: =SUMIFS(Returns!$G:$G,Returns!$B:$B,C5) | J5: =MAX(0,ABS(E5)-I5)
A6: 2026-05-21T11:00:00 | B6: Refund | C6: 111-4006547-6808666 | D6: TH-SILSPA-13 | E6: 1 | F6: -15.44 | G6: -13.59 | H6: =IFERROR(Windows!$B$2-DATEVALUE(LEFT(A6,10)),"") | I6: =SUMIFS(Returns!$G:$G,Returns!$B:$B,C6) | J6: =MAX(0,ABS(E6)-I6)
A7: 2026-05-22T22:00:00 | B7: Refund | C7: 111-4000215-7071290 | D7: TH-CASIRO-01 | E7: 1 | F7: -36.04 | G7: -31.72 | H7: =IFERROR(Windows!$B$2-DATEVALUE(LEFT(A7,10)),"") | I7: =SUMIFS(Returns!$G:$G,Returns!$B:$B,C7) | J7: =MAX(0,ABS(E7)-I7)
A8: 2026-05-24T07:00:00 | B8: Refund | C8: 111-4001074-3177903 | D8: TH-CASIRO-02 | E8: 1 | F8: -46.34 | G8: -40.78 | H8: =IFERROR(Windows!$B$2-DATEVALUE(LEFT(A8,10)),"") | I8: =SUMIFS(Returns!$G:$G,Returns!$B:$B,C8) | J8: =MAX(0,ABS(E8)-I8)
A9: 2026-05-24T10:00:00 | B9: Refund | C9: 111-4011691-1549916 | D9: TH-KITTOW-24 | E9: 1 | F9: -24.99 | G9: -21.99 | H9: =IFERROR(Windows!$B$2-DATEVALUE(LEFT(A9,10)),"") | I9: =SUMIFS(Returns!$G:$G,Returns!$B:$B,C9) | J9: =MAX(0,ABS(E9)-I9)
A10: 2026-05-24T19:00:00 | B10: Refund | C10: 111-4011334-2057147 | D10: TH-TRICOR-23 | E10: 1 | F10: -12.6 | G10: -11.09 | H10: =IFERROR(Windows!$B$2-DATEVALUE(LEFT(A10,10)),"") | I10: =SUMIFS(Returns!$G:$G,Returns!$B:$B,C10) | J10: =MAX(0,ABS(E10)-I10)
A11: 2026-05-25T07:00:00 | B11: Refund | C11: 111-4000397-3921245 | D11: TH-CASIRO-01 | E11: 1 | F11: -36.04 | G11: -31.72 | H11: =IFERROR(Windows!$B$2-DATEVALUE(LEFT(A11,10)),"") | I11: =SUMIFS(Returns!$G:$G,Returns!$B:$B,C11) | J11: =MAX(0,ABS(E11)-I11)
A12: 2026-05-25T08:00:00 | B12: Refund | C12: 111-4007866-6847779 | D12: TH-PEPMIL-16 | E12: 1 | F12: -33.98 | G12: -29.9 | H12: =IFERROR(Windows!$B$2-DATEVALUE(LEFT(A12,10)),"") | I12: =SUMIFS(Returns!$G:$G,Returns!$B:$B,C12) | J12: =MAX(0,ABS(E12)-I12)
A13: 2026-05-26T14:00:00 | B13: Refund | C13: 111-4006090-3906751 | D13: TH-STAMIX-12 | E13: 1 | F13: -38.1 | G13: -33.53 | H13: =IFERROR(Windows!$B$2-DATEVALUE(LEFT(A13,10)),"") | I13: =SUMIFS(Returns!$G:$G,Returns!$B:$B,C13) | J13: =MAX(0,ABS(E13)-I13)
... A149: 2026-08-27T15:00:00 | B149: Refund | C149: 111-4009157-6843329 | D149: TH-COFCAN-19 | E149: 1 | F149: -22.99 | G149: -20.23 | H149: =IFERROR(Windows!$B$2-DATEVALUE(LEFT(A149,10)),"") | I149: =SUMIFS(Returns!$G:$G,Returns!$B:$B,C149) | J149: =MAX(0,ABS(E149)-I149)

Sheet Claims
A1: Claim type | B1: SKU | C1: Event date | D1: Units | E1: Order id (refunds) | F1: Unit value | G1: Value | H1: Eligible from | I1: Deadline | J1: Days left | K1: Status | L1: P(approve) | M1: Expected value | N1: Value basis
A2: warehouse_lost | B2: TH-APRWAX-21 | C2: 46213 | D2: 21 | F2: =IFERROR(VLOOKUP(B2,COGS!$A$2:$G$25,7,FALSE),"") | G2: =IF(F2="","",D2*F2) | H2: =C2+VLOOKUP(A2,Windows!$A$24:$C$30,2,FALSE) | I2: =C2+VLOOKUP(A2,Windows!$A$24:$C$30,3,FALSE) | J2: =I2-Windows!$B$2 | K2: =IF(Windows!$B$2>I2,"expired",IF(Windows!$B$2<H2,"not_yet_eligible",IF(J2<=Windows!$B$9,"expiring","open"))) | L2: =VLOOKUP(A2,Windows!$A$15:$B$21,2,FALSE) | M2: =IF(G2="","",G2*L2) | N2: landed cost on file
A3: warehouse_lost | B3: TH-STAMIX-12 | C3: 46213 | D3: 18 | F3: =IFERROR(VLOOKUP(B3,COGS!$A$2:$G$25,7,FALSE),"") | G3: =IF(F3="","",D3*F3) | H3: =C3+VLOOKUP(A3,Windows!$A$24:$C$30,2,FALSE) | I3: =C3+VLOOKUP(A3,Windows!$A$24:$C$30,3,FALSE) | J3: =I3-Windows!$B$2 | K3: =IF(Windows!$B$2>I3,"expired",IF(Windows!$B$2<H3,"not_yet_eligible",IF(J3<=Windows!$B$9,"expiring","open"))) | L3: =VLOOKUP(A3,Windows!$A$15:$B$21,2,FALSE) | M3: =IF(G3="","",G3*L3) | N3: landed cost on file
A4: carrier_damaged | B4: TH-ENADUT-03 | C4: 46213 | D4: 8 | F4: =IFERROR(VLOOKUP(B4,COGS!$A$2:$G$25,7,FALSE),"") | G4: =IF(F4="","",D4*F4) | H4: =C4+VLOOKUP(A4,Windows!$A$24:$C$30,2,FALSE) | I4: =C4+VLOOKUP(A4,Windows!$A$24:$C$30,3,FALSE) | J4: =I4-Windows!$B$2 | K4: =IF(Windows!$B$2>I4,"expired",IF(Windows!$B$2<H4,"not_yet_eligible",IF(J4<=Windows!$B$9,"expiring","open"))) | L4: =VLOOKUP(A4,Windows!$A$15:$B$21,2,FALSE) | M4: =IF(G4="","",G4*L4) | N4: landed cost on file
A5: transit_lost | B5: TH-CASIRO-02 | C5: 46215 | D5: 11 | F5: =IFERROR(VLOOKUP(B5,COGS!$A$2:$G$25,7,FALSE),"") | G5: =IF(F5="","",D5*F5) | H5: =C5+VLOOKUP(A5,Windows!$A$24:$C$30,2,FALSE) | I5: =C5+VLOOKUP(A5,Windows!$A$24:$C$30,3,FALSE) | J5: =I5-Windows!$B$2 | K5: =IF(Windows!$B$2>I5,"expired",IF(Windows!$B$2<H5,"not_yet_eligible",IF(J5<=Windows!$B$9,"expiring","open"))) | L5: =VLOOKUP(A5,Windows!$A$15:$B$21,2,FALSE) | M5: =IF(G5="","",G5*L5) | N5: landed cost on file
A6: warehouse_lost | B6: TH-FREPRE-17 | C6: 46214 | D6: 16 | F6: =IFERROR(VLOOKUP(B6,COGS!$A$2:$G$25,7,FALSE),"") | G6: =IF(F6="","",D6*F6) | H6: =C6+VLOOKUP(A6,Windows!$A$24:$C$30,2,FALSE) | I6: =C6+VLOOKUP(A6,Windows!$A$24:$C$30,3,FALSE) | J6: =I6-Windows!$B$2 | K6: =IF(Windows!$B$2>I6,"expired",IF(Windows!$B$2<H6,"not_yet_eligible",IF(J6<=Windows!$B$9,"expiring","open"))) | L6: =VLOOKUP(A6,Windows!$A$15:$B$21,2,FALSE) | M6: =IF(G6="","",G6*L6) | N6: landed cost on file
A7: warehouse_lost | B7: TH-KITTOW-24 | C7: 46218 | D7: 20 | F7: =IFERROR(VLOOKUP(B7,COGS!$A$2:$G$25,7,FALSE),"") | G7: =IF(F7="","",D7*F7) | H7: =C7+VLOOKUP(A7,Windows!$A$24:$C$30,2,FALSE) | I7: =C7+VLOOKUP(A7,Windows!$A$24:$C$30,3,FALSE) | J7: =I7-Windows!$B$2 | K7: =IF(Windows!$B$2>I7,"expired",IF(Windows!$B$2<H7,"not_yet_eligible",IF(J7<=Windows!$B$9,"expiring","open"))) | L7: =VLOOKUP(A7,Windows!$A$15:$B$21,2,FALSE) | M7: =IF(G7="","",G7*L7) | N7: landed cost on file
A8: warehouse_lost | B8: TH-PARKNI-09 | C8: 46216 | D8: 25 | F8: =IFERROR(VLOOKUP(B8,COGS!$A$2:$G$25,7,FALSE),"") | G8: =IF(F8="","",D8*F8) | H8: =C8+VLOOKUP(A8,Windows!$A$24:$C$30,2,FALSE) | I8: =C8+VLOOKUP(A8,Windows!$A$24:$C$30,3,FALSE) | J8: =I8-Windows!$B$2 | K8: =IF(Windows!$B$2>I8,"expired",IF(Windows!$B$2<H8,"not_yet_eligible",IF(J8<=Windows!$B$9,"expiring","open"))) | L8: =VLOOKUP(A8,Windows!$A$15:$B$21,2,FALSE) | M8: =IF(G8="","",G8*L8) | N8: landed cost on file
A9: warehouse_lost | B9: TH-CHEKNI-08 | C9: 46217 | D9: 7 | F9: =IFERROR(VLOOKUP(B9,COGS!$A$2:$G$25,7,FALSE),"") | G9: =IF(F9="","",D9*F9) | H9: =C9+VLOOKUP(A9,Windows!$A$24:$C$30,2,FALSE) | I9: =C9+VLOOKUP(A9,Windows!$A$24:$C$30,3,FALSE) | J9: =I9-Windows!$B$2 | K9: =IF(Windows!$B$2>I9,"expired",IF(Windows!$B$2<H9,"not_yet_eligible",IF(J9<=Windows!$B$9,"expiring","open"))) | L9: =VLOOKUP(A9,Windows!$A$15:$B$21,2,FALSE) | M9: =IF(G9="","",G9*L9) | N9: landed cost on file
A10: warehouse_lost | B10: TH-COFCAN-19 | C10: 46214 | D10: 17 | F10: =IFERROR(VLOOKUP(B10,COGS!$A$2:$G$25,7,FALSE),"") | G10: =IF(F10="","",D10*F10) | H10: =C10+VLOOKUP(A10,Windows!$A$24:$C$30,2,FALSE) | I10: =C10+VLOOKUP(A10,Windows!$A$24:$C$30,3,FALSE) | J10: =I10-Windows!$B$2 | K10: =IF(Windows!$B$2>I10,"expired",IF(Windows!$B$2<H10,"not_yet_eligible",IF(J10<=Windows!$B$9,"expiring","open"))) | L10: =VLOOKUP(A10,Windows!$A$15:$B$21,2,FALSE) | M10: =IF(G10="","",G10*L10) | N10: landed cost on file
A11: carrier_damaged | B11: TH-PEPMIL-16 | C11: 46209 | D11: 13 | F11: =IFERROR(VLOOKUP(B11,COGS!$A$2:$G$25,7,FALSE),"") | G11: =IF(F11="","",D11*F11) | H11: =C11+VLOOKUP(A11,Windows!$A$24:$C$30,2,FALSE) | I11: =C11+VLOOKUP(A11,Windows!$A$24:$C$30,3,FALSE) | J11: =I11-Windows!$B$2 | K11: =IF(Windows!$B$2>I11,"expired",IF(Windows!$B$2<H11,"not_yet_eligible",IF(J11<=Windows!$B$9,"expiring","open"))) | L11: =VLOOKUP(A11,Windows!$A$15:$B$21,2,FALSE) | M11: =IF(G11="","",G11*L11) | N11: landed cost on file
A12: carrier_damaged | B12: TH-WALSER-07 | C12: 46208 | D12: 9 | F12: =IFERROR(VLOOKUP(B12,COGS!$A$2:$G$25,7,FALSE),"") | G12: =IF(F12="","",D12*F12) | H12: =C12+VLOOKUP(A12,Windows!$A$24:$C$30,2,FALSE) | I12: =C12+VLOOKUP(A12,Windows!$A$24:$C$30,3,FALSE) | J12: =I12-Windows!$B$2 | K12: =IF(Windows!$B$2>I12,"expired",IF(Windows!$B$2<H12,"not_yet_eligible",IF(J12<=Windows!$B$9,"expiring","open"))) | L12: =VLOOKUP(A12,Windows!$A$15:$B$21,2,FALSE) | M12: =IF(G12="","",G12*L12) | N12: landed cost on file
A13: transit_lost | B13: TH-CARSTE-04 | C13: 46211 | D13: 7 | F13: =IFERROR(VLOOKUP(B13,COGS!$A$2:$G$25,7,FALSE),"") | G13: =IF(F13="","",D13*F13) | H13: =C13+VLOOKUP(A13,Windows!$A$24:$C$30,2,FALSE) | I13: =C13+VLOOKUP(A13,Windows!$A$24:$C$30,3,FALSE) | J13: =I13-Windows!$B$2 | K13: =IF(Windows!$B$2>I13,"expired",IF(Windows!$B$2<H13,"not_yet_eligible",IF(J13<=Windows!$B$9,"expiring","open"))) | L13: =VLOOKUP(A13,Windows!$A$15:$B$21,2,FALSE) | M13: =IF(G13="","",G13*L13) | N13: landed cost on file
... A23: carrier_damaged | B23: TH-BAMCUT-05 | C23: 46213 | D23: 6 | F23: =IFERROR(VLOOKUP(B23,COGS!$A$2:$G$25,7,FALSE),"") | G23: =IF(F23="","",D23*F23) | H23: =C23+VLOOKUP(A23,Windows!$A$24:$C$30,2,FALSE) | I23: =C23+VLOOKUP(A23,Windows!$A$24:$C$30,3,FALSE) | J23: =I23-Windows!$B$2 | K23: =IF(Windows!$B$2>I23,"expired",IF(Windows!$B$2<H23,"not_yet_eligible",IF(J23<=Windows!$B$9,"expiring","open"))) | L23: =VLOOKUP(A23,Windows!$A$15:$B$21,2,FALSE) | M23: =IF(G23="","",G23*L23) | N23: landed cost on file
A24: refund_no_return | B24: TH-CASIRO-02 | C24: 46150 | D24: 1 | E24: 111-4001167-4531939 | F24: 46.34 | G24: =IF(F24="","",D24*F24) | H24: =C24+VLOOKUP(A24,Windows!$A$24:$C$30,2,FALSE) | I24: =C24+VLOOKUP(A24,Windows!$A$24:$C$30,3,FALSE) | J24: =I24-Windows!$B$2 | K24: =IF(Windows!$B$2>I24,"expired",IF(Windows!$B$2<H24,"not_yet_eligible",IF(J24<=Windows!$B$9,"expiring","open"))) | L24: =VLOOKUP(A24,Windows!$A$15:$B$21,2,FALSE) | M24: =IF(G24="","",G24*L24) | N24: refunded amount per unit — Amazon reimburses at its determined value, so this is the ceiling
A25: refund_no_return | B25: TH-POUOVE-18 | C25: 46157 | D25: 1 | E25: 111-4008814-6418098 | F25: 44.28 | G25: =IF(F25="","",D25*F25) | H25: =C25+VLOOKUP(A25,Windows!$A$24:$C$30,2,FALSE) | I25: =C25+VLOOKUP(A25,Windows!$A$24:$C$30,3,FALSE) | J25: =I25-Windows!$B$2 | K25: =IF(Windows!$B$2>I25,"expired",IF(Windows!$B$2<H25,"not_yet_eligible",IF(J25<=Windows!$B$9,"expiring","open"))) | L25: =VLOOKUP(A25,Windows!$A$15:$B$21,2,FALSE) | M25: =IF(G25="","",G25*L25) | N25: refunded amount per unit — Amazon reimburses at its determined value, so this is the ceiling
A26: carrier_damaged | B26: TH-PARKNI-09 | C26: 46214 | D26: 9 | F26: =IFERROR(VLOOKUP(B26,COGS!$A$2:$G$25,7,FALSE),"") | G26: =IF(F26="","",D26*F26) | H26: =C26+VLOOKUP(A26,Windows!$A$24:$C$30,2,FALSE) | I26: =C26+VLOOKUP(A26,Windows!$A$24:$C$30,3,FALSE) | J26: =I26-Windows!$B$2 | K26: =IF(Windows!$B$2>I26,"expired",IF(Windows!$B$2<H26,"not_yet_eligible",IF(J26<=Windows!$B$9,"expiring","open"))) | L26: =VLOOKUP(A26,Windows!$A$15:$B$21,2,FALSE) | M26: =IF(G26="","",G26*L26) | N26: landed cost on file
A27: warehouse_lost | B27: TH-TRICOR-23 | C27: 46214 | D27: 8 | F27: =IFERROR(VLOOKUP(B27,COGS!$A$2:$G$25,7,FALSE),"") | G27: =IF(F27="","",D27*F27) | H27: =C27+VLOOKUP(A27,Windows!$A$24:$C$30,2,FALSE) | I27: =C27+VLOOKUP(A27,Windows!$A$24:$C$30,3,FALSE) | J27: =I27-Windows!$B$2 | K27: =IF(Windows!$B$2>I27,"expired",IF(Windows!$B$2<H27,"not_yet_eligible",IF(J27<=Windows!$B$9,"expiring","open"))) | L27: =VLOOKUP(A27,Windows!$A$15:$B$21,2,FALSE) | M27: =IF(G27="","",G27*L27) | N27: landed cost on file
A28: carrier_damaged | B28: TH-TRICOR-23 | C28: 46213 | D28: 8 | F28: =IFERROR(VLOOKUP(B28,COGS!$A$2:$G$25,7,FALSE),"") | G28: =IF(F28="","",D28*F28) | H28: =C28+VLOOKUP(A28,Windows!$A$24:$C$30,2,FALSE) | I28: =C28+VLOOKUP(A28,Windows!$A$24:$C$30,3,FALSE) | J28: =I28-Windows!$B$2 | K28: =IF(Windows!$B$2>I28,"expired",IF(Windows!$B$2<H28,"not_yet_eligible",IF(J28<=Windows!$B$9,"expiring","open"))) | L28: =VLOOKUP(A28,Windows!$A$15:$B$21,2,FALSE) | M28: =IF(G28="","",G28*L28) | N28: landed cost on file
A29: carrier_damaged | B29: TH-KNISHA-11 | C29: 46210 | D29: 3 | F29: =IFERROR(VLOOKUP(B29,COGS!$A$2:$G$25,7,FALSE),"") | G29: =IF(F29="","",D29*F29) | H29: =C29+VLOOKUP(A29,Windows!$A$24:$C$30,2,FALSE) | I29: =C29+VLOOKUP(A29,Windows!$A$24:$C$30,3,FALSE) | J29: =I29-Windows!$B$2 | K29: =IF(Windows!$B$2>I29,"expired",IF(Windows!$B$2<H29,"not_yet_eligible",IF(J29<=Windows!$B$9,"expiring","open"))) | L29: =VLOOKUP(A29,Windows!$A$15:$B$21,2,FALSE) | M29: =IF(G29="","",G29*L29) | N29: landed cost on file
A30: carrier_damaged | B30: TH-OVEMIT-22 | C30: 46209 | D30: 4 | F30: =IFERROR(VLOOKUP(B30,COGS!$A$2:$G$25,7,FALSE),"") | G30: =IF(F30="","",D30*F30) | H30: =C30+VLOOKUP(A30,Windows!$A$24:$C$30,2,FALSE) | I30: =C30+VLOOKUP(A30,Windows!$A$24:$C$30,3,FALSE) | J30: =I30-Windows!$B$2 | K30: =IF(Windows!$B$2>I30,"expired",IF(Windows!$B$2<H30,"not_yet_eligible",IF(J30<=Windows!$B$9,"expiring","open"))) | L30: =VLOOKUP(A30,Windows!$A$15:$B$21,2,FALSE) | M30: =IF(G30="","",G30*L30) | N30: landed cost on file
A31: refund_no_return | B31: TH-PARKNI-09 | C31: 46154 | D31: 1 | E31: 111-4004228-2926992 | F31: 18.42 | G31: =IF(F31="","",D31*F31) | H31: =C31+VLOOKUP(A31,Windows!$A$24:$C$30,2,FALSE) | I31: =C31+VLOOKUP(A31,Windows!$A$24:$C$30,3,FALSE) | J31: =I31-Windows!$B$2 | K31: =IF(Windows!$B$2>I31,"expired",IF(Windows!$B$2<H31,"not_yet_eligible",IF(J31<=Windows!$B$9,"expiring","open"))) | L31: =VLOOKUP(A31,Windows!$A$15:$B$21,2,FALSE) | M31: =IF(G31="","",G31*L31) | N31: refunded amount per unit — Amazon reimburses at its determined value, so this is the ceiling
A32: refund_no_return | B32: TH-SILSPA-13 | C32: 46153 | D32: 1 | E32: 111-4006638-6018624 | F32: 15.44 | G32: =IF(F32="","",D32*F32) | H32: =C32+VLOOKUP(A32,Windows!$A$24:$C$30,2,FALSE) | I32: =C32+VLOOKUP(A32,Windows!$A$24:$C$30,3,FALSE) | J32: =I32-Windows!$B$2 | K32: =IF(Windows!$B$2>I32,"expired",IF(Windows!$B$2<H32,"not_yet_eligible",IF(J32<=Windows!$B$9,"expiring","open"))) | L32: =VLOOKUP(A32,Windows!$A$15:$B$21,2,FALSE) | M32: =IF(G32="","",G32*L32) | N32: refunded amount per unit — Amazon reimburses at its determined value, so this is the ceiling
A33: damaged_return | B33: TH-WALSER-07 | C33: 46219 | D33: 1 | E33: 111-4003317-9770649 | F33: =IFERROR(VLOOKUP(B33,COGS!$A$2:$G$25,7,FALSE),"") | G33: =IF(F33="","",D33*F33) | H33: =C33+VLOOKUP(A33,Windows!$A$24:$C$30,2,FALSE) | I33: =C33+VLOOKUP(A33,Windows!$A$24:$C$30,3,FALSE) | J33: =I33-Windows!$B$2 | K33: =IF(Windows!$B$2>I33,"expired",IF(Windows!$B$2<H33,"not_yet_eligible",IF(J33<=Windows!$B$9,"expiring","open"))) | L33: =VLOOKUP(A33,Windows!$A$15:$B$21,2,FALSE) | M33: =IF(G33="","",G33*L33) | N33: landed cost on file
A34: damaged_return | B34: TH-CASIRO-01 | C34: 46209 | D34: 1 | E34: 111-4000172-1485759 | F34: =IFERROR(VLOOKUP(B34,COGS!$A$2:$G$25,7,FALSE),"") | G34: =IF(F34="","",D34*F34) | H34: =C34+VLOOKUP(A34,Windows!$A$24:$C$30,2,FALSE) | I34: =C34+VLOOKUP(A34,Windows!$A$24:$C$30,3,FALSE) | J34: =I34-Windows!$B$2 | K34: =IF(Windows!$B$2>I34,"expired",IF(Windows!$B$2<H34,"not_yet_eligible",IF(J34<=Windows!$B$9,"expiring","open"))) | L34: =VLOOKUP(A34,Windows!$A$15:$B$21,2,FALSE) | M34: =IF(G34="","",G34*L34) | N34: landed cost on file
A35: damaged_return | B35: TH-APRWAX-21 | C35: 46220 | D35: 1 | E35: 111-4010212-9353804 | F35: =IFERROR(VLOOKUP(B35,COGS!$A$2:$G$25,7,FALSE),"") | G35: =IF(F35="","",D35*F35) | H35: =C35+VLOOKUP(A35,Windows!$A$24:$C$30,2,FALSE) | I35: =C35+VLOOKUP(A35,Windows!$A$24:$C$30,3,FALSE) | J35: =I35-Windows!$B$2 | K35: =IF(Windows!$B$2>I35,"expired",IF(Windows!$B$2<H35,"not_yet_eligible",IF(J35<=Windows!$B$9,"expiring","open"))) | L35: =VLOOKUP(A35,Windows!$A$15:$B$21,2,FALSE) | M35: =IF(G35="","",G35*L35) | N35: landed cost on file
A36: damaged_return | B36: TH-COFCAN-19 | C36: 46212 | D36: 1 | E36: 111-4009121-3689668 | F36: =IFERROR(VLOOKUP(B36,COGS!$A$2:$G$25,7,FALSE),"") | G36: =IF(F36="","",D36*F36) | H36: =C36+VLOOKUP(A36,Windows!$A$24:$C$30,2,FALSE) | I36: =C36+VLOOKUP(A36,Windows!$A$24:$C$30,3,FALSE) | J36: =I36-Windows!$B$2 | K36: =IF(Windows!$B$2>I36,"expired",IF(Windows!$B$2<H36,"not_yet_eligible",IF(J36<=Windows!$B$9,"expiring","open"))) | L36: =VLOOKUP(A36,Windows!$A$15:$B$21,2,FALSE) | M36: =IF(G36="","",G36*L36) | N36: landed cost on file
A37: damaged_return | B37: TH-COFCAN-19 | C37: 46209 | D37: 1 | E37: 111-4009221-3909542 | F37: =IFERROR(VLOOKUP(B37,COGS!$A$2:$G$25,7,FALSE),"") | G37: =IF(F37="","",D37*F37) | H37: =C37+VLOOKUP(A37,Windows!$A$24:$C$30,2,FALSE) | I37: =C37+VLOOKUP(A37,Windows!$A$24:$C$30,3,FALSE) | J37: =I37-Windows!$B$2 | K37: =IF(Windows!$B$2>I37,"expired",IF(Windows!$B$2<H37,"not_yet_eligible",IF(J37<=Windows!$B$9,"expiring","open"))) | L37: =VLOOKUP(A37,Windows!$A$15:$B$21,2,FALSE) | M37: =IF(G37="","",G37*L37) | N37: landed cost on file
A38: damaged_return | B38: TH-OVEMIT-22 | C38: 46216 | D38: 1 | E38: 111-4010585-7573195 | F38: =IFERROR(VLOOKUP(B38,COGS!$A$2:$G$25,7,FALSE),"") | G38: =IF(F38="","",D38*F38) | H38: =C38+VLOOKUP(A38,Windows!$A$24:$C$30,2,FALSE) | I38: =C38+VLOOKUP(A38,Windows!$A$24:$C$30,3,FALSE) | J38: =I38-Windows!$B$2 | K38: =IF(Windows!$B$2>I38,"expired",IF(Windows!$B$2<H38,"not_yet_eligible",IF(J38<=Windows!$B$9,"expiring","open"))) | L38: =VLOOKUP(A38,Windows!$A$15:$B$21,2,FALSE) | M38: =IF(G38="","",G38*L38) | N38: landed cost on file
A39: warehouse_lost | B39: TH-CARSTE-04 | C39: 46230 | D39: 18 | F39: =IFERROR(VLOOKUP(B39,COGS!$A$2:$G$25,7,FALSE),"") | G39: =IF(F39="","",D39*F39) | H39: =C39+VLOOKUP(A39,Windows!$A$24:$C$30,2,FALSE) | I39: =C39+VLOOKUP(A39,Windows!$A$24:$C$30,3,FALSE) | J39: =I39-Windows!$B$2 | K39: =IF(Windows!$B$2>I39,"expired",IF(Windows!$B$2<H39,"not_yet_eligible",IF(J39<=Windows!$B$9,"expiring","open"))) | L39: =VLOOKUP(A39,Windows!$A$15:$B$21,2,FALSE) | M39: =IF(G39="","",G39*L39) | N39: landed cost on file
A40: warehouse_lost | B40: TH-POUOVE-18 | C40: 46227 | D40: 18 | F40: =IFERROR(VLOOKUP(B40,COGS!$A$2:$G$25,7,FALSE),"") | G40: =IF(F40="","",D40*F40) | H40: =C40+VLOOKUP(A40,Windows!$A$24:$C$30,2,FALSE) | I40: =C40+VLOOKUP(A40,Windows!$A$24:$C$30,3,FALSE) | J40: =I40-Windows!$B$2 | K40: =IF(Windows!$B$2>I40,"expired",IF(Windows!$B$2<H40,"not_yet_eligible",IF(J40<=Windows!$B$9,"expiring","open"))) | L40: =VLOOKUP(A40,Windows!$A$15:$B$21,2,FALSE) | M40: =IF(G40="","",G40*L40) | N40: landed cost on file
A41: warehouse_lost | B41: TH-ENADUT-03 | C41: 46230 | D41: 8 | F41: =IFERROR(VLOOKUP(B41,COGS!$A$2:$G$25,7,FALSE),"") | G41: =IF(F41="","",D41*F41) | H41: =C41+VLOOKUP(A41,Windows!$A$24:$C$30,2,FALSE) | I41: =C41+VLOOKUP(A41,Windows!$A$24:$C$30,3,FALSE) | J41: =I41-Windows!$B$2 | K41: =IF(Windows!$B$2>I41,"expired",IF(Windows!$B$2<H41,"not_yet_eligible",IF(J41<=Windows!$B$9,"expiring","open"))) | L41: =VLOOKUP(A41,Windows!$A$15:$B$21,2,FALSE) | M41: =IF(G41="","",G41*L41) | N41: landed cost on file
A42: warehouse_lost | B42: TH-PEPMIL-16 | C42: 46227 | D42: 18 | F42: =IFERROR(VLOOKUP(B42,COGS!$A$2:$G$25,7,FALSE),"") | G42: =IF(F42="","",D42*F42) | H42: =C42+VLOOKUP(A42,Windows!$A$24:$C$30,2,FALSE) | I42: =C42+VLOOKUP(A42,Windows!$A$24:$C$30,3,FALSE) | J42: =I42-Windows!$B$2 | K42: =IF(Windows!$B$2>I42,"expired",IF(Windows!$B$2<H42,"not_yet_eligible",IF(J42<=Windows!$B$9,"expiring","open"))) | L42: =VLOOKUP(A42,Windows!$A$15:$B$21,2,FALSE) | M42: =IF(G42="","",G42*L42) | N42: landed cost on file
A43: warehouse_lost | B43: TH-WALSER-07 | C43: 46226 | D43: 7 | F43: =IFERROR(VLOOKUP(B43,COGS!$A$2:$G$25,7,FALSE),"") | G43: =IF(F43="","",D43*F43) | H43: =C43+VLOOKUP(A43,Windows!$A$24:$C$30,2,FALSE) | I43: =C43+VLOOKUP(A43,Windows!$A$24:$C$30,3,FALSE) | J43: =I43-Windows!$B$2 | K43: =IF(Windows!$B$2>I43,"expired",IF(Windows!$B$2<H43,"not_yet_eligible",IF(J43<=Windows!$B$9,"expiring","open"))) | L43: =VLOOKUP(A43,Windows!$A$15:$B$21,2,FALSE) | M43: =IF(G43="","",G43*L43) | N43: landed cost on file
A44: warehouse_lost | B44: TH-BAMCUT-06 | C44: 46221 | D44: 15 | F44: =IFERROR(VLOOKUP(B44,COGS!$A$2:$G$25,7,FALSE),"") | G44: =IF(F44="","",D44*F44) | H44: =C44+VLOOKUP(A44,Windows!$A$24:$C$30,2,FALSE) | I44: =C44+VLOOKUP(A44,Windows!$A$24:$C$30,3,FALSE) | J44: =I44-Windows!$B$2 | K44: =IF(Windows!$B$2>I44,"expired",IF(Windows!$B$2<H44,"not_yet_eligible",IF(J44<=Windows!$B$9,"expiring","open"))) | L44: =VLOOKUP(A44,Windows!$A$15:$B$21,2,FALSE) | M44: =IF(G44="","",G44*L44) | N44: landed cost on file
A45: warehouse_lost | B45: TH-SALCEL-15 | C45: 46231 | D45: 18 | F45: =IFERROR(VLOOKUP(B45,COGS!$A$2:$G$25,7,FALSE),"") | G45: =IF(F45="","",D45*F45) | H45: =C45+VLOOKUP(A45,Windows!$A$24:$C$30,2,FALSE) | I45: =C45+VLOOKUP(A45,Windows!$A$24:$C$30,3,FALSE) | J45: =I45-Windows!$B$2 | K45: =IF(Windows!$B$2>I45,"expired",IF(Windows!$B$2<H45,"not_yet_eligible",IF(J45<=Windows!$B$9,"expiring","open"))) | L45: =VLOOKUP(A45,Windows!$A$15:$B$21,2,FALSE) | M45: =IF(G45="","",G45*L45) | N45: landed cost on file
A46: refund_no_return | B46: TH-CARSTE-04 | C46: 46188 | D46: 1 | E46: 111-4001943-4629004 | F46: 51.49 | G46: =IF(F46="","",D46*F46) | H46: =C46+VLOOKUP(A46,Windows!$A$24:$C$30,2,FALSE) | I46: =C46+VLOOKUP(A46,Windows!$A$24:$C$30,3,FALSE) | J46: =I46-Windows!$B$2 | K46: =IF(Windows!$B$2>I46,"expired",IF(Windows!$B$2<H46,"not_yet_eligible",IF(J46<=Windows!$B$9,"expiring","open"))) | L46: =VLOOKUP(A46,Windows!$A$15:$B$21,2,FALSE) | M46: =IF(G46="","",G46*L46) | N46: refunded amount per unit — Amazon reimburses at its determined value, so this is the ceiling
A47: refund_no_return | B47: TH-POUOVE-18 | C47: 46206 | D47: 1 | E47: 111-4008775-1999468 | F47: 44.28 | G47: =IF(F47="","",D47*F47) | H47: =C47+VLOOKUP(A47,Windows!$A$24:$C$30,2,FALSE) | I47: =C47+VLOOKUP(A47,Windows!$A$24:$C$30,3,FALSE) | J47: =I47-Windows!$B$2 | K47: =IF(Windows!$B$2>I47,"expired",IF(Windows!$B$2<H47,"not_yet_eligible",IF(J47<=Windows!$B$9,"expiring","open"))) | L47: =VLOOKUP(A47,Windows!$A$15:$B$21,2,FALSE) | M47: =IF(G47="","",G47*L47) | N47: refunded amount per unit — Amazon reimburses at its determined value, so this is the ceiling
A48: refund_no_return | B48: TH-WALSER-07 | C48: 46206 | D48: 1 | E48: 111-4003456-9226073 | F48: 37.82 | G48: =IF(F48="","",D48*F48) | H48: =C48+VLOOKUP(A48,Windows!$A$24:$C$30,2,FALSE) | I48: =C48+VLOOKUP(A48,Windows!$A$24:$C$30,3,FALSE) | J48: =I48-Windows!$B$2 | K48: =IF(Windows!$B$2>I48,"expired",IF(Windows!$B$2<H48,"not_yet_eligible",IF(J48<=Windows!$B$9,"expiring","open"))) | L48: =VLOOKUP(A48,Windows!$A$15:$B$21,2,FALSE) | M48: =IF(G48="","",G48*L48) | N48: refunded amount per unit — Amazon reimburses at its determined value, so this is the ceiling
A49: refund_no_return | B49: TH-CASIRO-01 | C49: 46197 | D49: 1 | E49: 111-4000554-9214500 | F49: 36.04 | G49: =IF(F49="","",D49*F49) | H49: =C49+VLOOKUP(A49,Windows!$A$24:$C$30,2,FALSE) | I49: =C49+VLOOKUP(A49,Windows!$A$24:$C$30,3,FALSE) | J49: =I49-Windows!$B$2 | K49: =IF(Windows!$B$2>I49,"expired",IF(Windows!$B$2<H49,"not_yet_eligible",IF(J49<=Windows!$B$9,"expiring","open"))) | L49: =VLOOKUP(A49,Windows!$A$15:$B$21,2,FALSE) | M49: =IF(G49="","",G49*L49) | N49: refunded amount per unit — Amazon reimburses at its determined value, so this is the ceiling
A50: refund_no_return | B50: TH-PEPMIL-16 | C50: 46177 | D50: 1 | E50: 111-4007881-1390064 | F50: 33.98 | G50: =IF(F50="","",D50*F50) | H50: =C50+VLOOKUP(A50,Windows!$A$24:$C$30,2,FALSE) | I50: =C50+VLOOKUP(A50,Windows!$A$24:$C$30,3,FALSE) | J50: =I50-Windows!$B$2 | K50: =IF(Windows!$B$2>I50,"expired",IF(Windows!$B$2<H50,"not_yet_eligible",IF(J50<=Windows!$B$9,"expiring","open"))) | L50: =VLOOKUP(A50,Windows!$A$15:$B$21,2,FALSE) | M50: =IF(G50="","",G50*L50) | N50: refunded amount per unit — Amazon reimburses at its determined value, so this is the ceiling
A51: refund_no_return | B51: TH-PEPMIL-16 | C51: 46172 | D51: 1 | E51: 111-4007916-2698823 | F51: 33.98 | G51: =IF(F51="","",D51*F51) | H51: =C51+VLOOKUP(A51,Windows!$A$24:$C$30,2,FALSE) | I51: =C51+VLOOKUP(A51,Windows!$A$24:$C$30,3,FALSE) | J51: =I51-Windows!$B$2 | K51: =IF(Windows!$B$2>I51,"expired",IF(Windows!$B$2<H51,"not_yet_eligible",IF(J51<=Windows!$B$9,"expiring","open"))) | L51: =VLOOKUP(A51,Windows!$A$15:$B$21,2,FALSE) | M51: =IF(G51="","",G51*L51) | N51: refunded amount per unit — Amazon reimburses at its determined value, so this is the ceiling
A52: warehouse_lost | B52: TH-KNISHA-11 | C52: 46223 | D52: 4 | F52: =IFERROR(VLOOKUP(B52,COGS!$A$2:$G$25,7,FALSE),"") | G52: =IF(F52="","",D52*F52) | H52: =C52+VLOOKUP(A52,Windows!$A$24:$C$30,2,FALSE) | I52: =C52+VLOOKUP(A52,Windows!$A$24:$C$30,3,FALSE) | J52: =I52-Windows!$B$2 | K52: =IF(Windows!$B$2>I52,"expired",IF(Windows!$B$2<H52,"not_yet_eligible",IF(J52<=Windows!$B$9,"expiring","open"))) | L52: =VLOOKUP(A52,Windows!$A$15:$B$21,2,FALSE) | M52: =IF(G52="","",G52*L52) | N52: landed cost on file
A53: refund_no_return | B53: TH-BAMCUT-05 | C53: 46174 | D53: 1 | E53: 111-4002457-7315217 | F53: 27.15 | G53: =IF(F53="","",D53*F53) | H53: =C53+VLOOKUP(A53,Windows!$A$24:$C$30,2,FALSE) | I53: =C53+VLOOKUP(A53,Windows!$A$24:$C$30,3,FALSE) | J53: =I53-Windows!$B$2 | K53: =IF(Windows!$B$2>I53,"expired",IF(Windows!$B$2<H53,"not_yet_eligible",IF(J53<=Windows!$B$9,"expiring","open"))) | L53: =VLOOKUP(A53,Windows!$A$15:$B$21,2,FALSE) | M53: =IF(G53="","",G53*L53) | N53: refunded amount per unit — Amazon reimburses at its determined value, so this is the ceiling
A54: refund_no_return | B54: TH-KNISHA-11 | C54: 46171 | D54: 1 | E54: 111-4005571-5972185 | F54: 24.99 | G54: =IF(F54="","",D54*F54) | H54: =C54+VLOOKUP(A54,Windows!$A$24:$C$30,2,FALSE) | I54: =C54+VLOOKUP(A54,Windows!$A$24:$C$30,3,FALSE) | J54: =I54-Windows!$B$2 | K54: =IF(Windows!$B$2>I54,"expired",IF(Windows!$B$2<H54,"not_yet_eligible",IF(J54<=Windows!$B$9,"expiring","open"))) | L54: =VLOOKUP(A54,Windows!$A$15:$B$21,2,FALSE) | M54: =IF(G54="","",G54*L54) | N54: refunded amount per unit — Amazon reimburses at its determined value, so this is the ceiling
A55: reimbursement_reversal | B55: TH-CARSTE-04 | C55: 46254 | D55: 2 | F55: 16.1 | G55: =IF(F55="","",D55*F55) | H55: =C55+VLOOKUP(A55,Windows!$A$24:$C$30,2,FALSE) | I55: =C55+VLOOKUP(A55,Windows!$A$24:$C$30,3,FALSE) | J55: =I55-Windows!$B$2 | K55: =IF(Windows!$B$2>I55,"expired",IF(Windows!$B$2<H55,"not_yet_eligible",IF(J55<=Windows!$B$9,"expiring","open"))) | L55: =VLOOKUP(A55,Windows!$A$15:$B$21,2,FALSE) | M55: =IF(G55="","",G55*L55) | N55: the reversed reimbursement amount
A56: refund_no_return | B56: TH-COFCAN-19 | C56: 46197 | D56: 1 | E56: 111-4009307-7052931 | F56: 22.99 | G56: =IF(F56="","",D56*F56) | H56: =C56+VLOOKUP(A56,Windows!$A$24:$C$30,2,FALSE) | I56: =C56+VLOOKUP(A56,Windows!$A$24:$C$30,3,FALSE) | J56: =I56-Windows!$B$2 | K56: =IF(Windows!$B$2>I56,"expired",IF(Windows!$B$2<H56,"not_yet_eligible",IF(J56<=Windows!$B$9,"expiring","open"))) | L56: =VLOOKUP(A56,Windows!$A$15:$B$21,2,FALSE) | M56: =IF(G56="","",G56*L56) | N56: refunded amount per unit — Amazon reimburses at its determined value, so this is the ceiling
A57: refund_no_return | B57: TH-COFCAN-19 | C57: 46200 | D57: 1 | E57: 111-4009338-4759944 | F57: 22.99 | G57: =IF(F57="","",D57*F57) | H57: =C57+VLOOKUP(A57,Windows!$A$24:$C$30,2,FALSE) | I57: =C57+VLOOKUP(A57,Windows!$A$24:$C$30,3,FALSE) | J57: =I57-Windows!$B$2 | K57: =IF(Windows!$B$2>I57,"expired",IF(Windows!$B$2<H57,"not_yet_eligible",IF(J57<=Windows!$B$9,"expiring","open"))) | L57: =VLOOKUP(A57,Windows!$A$15:$B$21,2,FALSE) | M57: =IF(G57="","",G57*L57) | N57: refunded amount per unit — Amazon reimburses at its determined value, so this is the ceiling
A58: refund_no_return | B58: TH-MEACUP-14 | C58: 46196 | D58: 1 | E58: 111-4007143-6810141 | F58: 21.33 | G58: =IF(F58="","",D58*F58) | H58: =C58+VLOOKUP(A58,Windows!$A$24:$C$30,2,FALSE) | I58: =C58+VLOOKUP(A58,Windows!$A$24:$C$30,3,FALSE) | J58: =I58-Windows!$B$2 | K58: =IF(Windows!$B$2>I58,"expired",IF(Windows!$B$2<H58,"not_yet_eligible",IF(J58<=Windows!$B$9,"expiring","open"))) | L58: =VLOOKUP(A58,Windows!$A$15:$B$21,2,FALSE) | M58: =IF(G58="","",G58*L58) | N58: refunded amount per unit — Amazon reimburses at its determined value, so this is the ceiling
A59: refund_no_return | B59: TH-OVEMIT-22 | C59: 46196 | D59: 1 | E59: 111-4010735-9520448 | F59: 19.99 | G59: =IF(F59="","",D59*F59) | H59: =C59+VLOOKUP(A59,Windows!$A$24:$C$30,2,FALSE) | I59: =C59+VLOOKUP(A59,Windows!$A$24:$C$30,3,FALSE) | J59: =I59-Windows!$B$2 | K59: =IF(Windows!$B$2>I59,"expired",IF(Windows!$B$2<H59,"not_yet_eligible",IF(J59<=Windows!$B$9,"expiring","open"))) | L59: =VLOOKUP(A59,Windows!$A$15:$B$21,2,FALSE) | M59: =IF(G59="","",G59*L59) | N59: refunded amount per unit — Amazon reimburses at its determined value, so this is the ceiling
A60: refund_no_return | B60: TH-OVEMIT-22 | C60: 46180 | D60: 1 | E60: 111-4010769-9828062 | F60: 19.99 | G60: =IF(F60="","",D60*F60) | H60: =C60+VLOOKUP(A60,Windows!$A$24:$C$30,2,FALSE) | I60: =C60+VLOOKUP(A60,Windows!$A$24:$C$30,3,FALSE) | J60: =I60-Windows!$B$2 | K60: =IF(Windows!$B$2>I60,"expired",IF(Windows!$B$2<H60,"not_yet_eligible",IF(J60<=Windows!$B$9,"expiring","open"))) | L60: =VLOOKUP(A60,Windows!$A$15:$B$21,2,FALSE) | M60: =IF(G60="","",G60*L60) | N60: refunded amount per unit — Amazon reimburses at its determined value, so this is the ceiling
A61: refund_no_return | B61: TH-BAMCUT-06 | C61: 46168 | D61: 1 | E61: 111-4002936-4262588 | F61: 19.39 | G61: =IF(F61="","",D61*F61) | H61: =C61+VLOOKUP(A61,Windows!$A$24:$C$30,2,FALSE) | I61: =C61+VLOOKUP(A61,Windows!$A$24:$C$30,3,FALSE) | J61: =I61-Windows!$B$2 | K61: =IF(Windows!$B$2>I61,"expired",IF(Windows!$B$2<H61,"not_yet_eligible",IF(J61<=Windows!$B$9,"expiring","open"))) | L61: =VLOOKUP(A61,Windows!$A$15:$B$21,2,FALSE) | M61: =IF(G61="","",G61*L61) | N61: refunded amount per unit — Amazon reimburses at its determined value, so this is the ceiling
A62: refund_no_return | B62: TH-BAMCUT-06 | C62: 46190 | D62: 1 | E62: 111-4002974-3278725 | F62: 19.39 | G62: =IF(F62="","",D62*F62) | H62: =C62+VLOOKUP(A62,Windows!$A$24:$C$30,2,FALSE) | I62: =C62+VLOOKUP(A62,Windows!$A$24:$C$30,3,FALSE) | J62: =I62-Windows!$B$2 | K62: =IF(Windows!$B$2>I62,"expired",IF(Windows!$B$2<H62,"not_yet_eligible",IF(J62<=Windows!$B$9,"expiring","open"))) | L62: =VLOOKUP(A62,Windows!$A$15:$B$21,2,FALSE) | M62: =IF(G62="","",G62*L62) | N62: refunded amount per unit — Amazon reimburses at its determined value, so this is the ceiling
A63: refund_no_return | B63: TH-TEAINF-20 | C63: 46204 | D63: 1 | E63: 111-4009824-6290224 | F63: 18.53 | G63: =IF(F63="","",D63*F63) | H63: =C63+VLOOKUP(A63,Windows!$A$24:$C$30,2,FALSE) | I63: =C63+VLOOKUP(A63,Windows!$A$24:$C$30,3,FALSE) | J63: =I63-Windows!$B$2 | K63: =IF(Windows!$B$2>I63,"expired",IF(Windows!$B$2<H63,"not_yet_eligible",IF(J63<=Windows!$B$9,"expiring","open"))) | L63: =VLOOKUP(A63,Windows!$A$15:$B$21,2,FALSE) | M63: =IF(G63="","",G63*L63) | N63: refunded amount per unit — Amazon reimburses at its determined value, so this is the ceiling
A64: damaged_return | B64: TH-CASIRO-02 | C64: 46227 | D64: 1 | E64: 111-4000777-9624660 | F64: =IFERROR(VLOOKUP(B64,COGS!$A$2:$G$25,7,FALSE),"") | G64: =IF(F64="","",D64*F64) | H64: =C64+VLOOKUP(A64,Windows!$A$24:$C$30,2,FALSE) | I64: =C64+VLOOKUP(A64,Windows!$A$24:$C$30,3,FALSE) | J64: =I64-Windows!$B$2 | K64: =IF(Windows!$B$2>I64,"expired",IF(Windows!$B$2<H64,"not_yet_eligible",IF(J64<=Windows!$B$9,"expiring","open"))) | L64: =VLOOKUP(A64,Windows!$A$15:$B$21,2,FALSE) | M64: =IF(G64="","",G64*L64) | N64: landed cost on file
A65: damaged_return | B65: TH-CARSTE-04 | C65: 46260 | D65: 1 | E65: 111-4001862-1379626 | F65: =IFERROR(VLOOKUP(B65,COGS!$A$2:$G$25,7,FALSE),"") | G65: =IF(F65="","",D65*F65) | H65: =C65+VLOOKUP(A65,Windows!$A$24:$C$30,2,FALSE) | I65: =C65+VLOOKUP(A65,Windows!$A$24:$C$30,3,FALSE) | J65: =I65-Windows!$B$2 | K65: =IF(Windows!$B$2>I65,"expired",IF(Windows!$B$2<H65,"not_yet_eligible",IF(J65<=Windows!$B$9,"expiring","open"))) | L65: =VLOOKUP(A65,Windows!$A$15:$B$21,2,FALSE) | M65: =IF(G65="","",G65*L65) | N65: landed cost on file
A66: damaged_return | B66: TH-CARSTE-04 | C66: 46255 | D66: 1 | E66: 111-4001893-6364951 | F66: =IFERROR(VLOOKUP(B66,COGS!$A$2:$G$25,7,FALSE),"") | G66: =IF(F66="","",D66*F66) | H66: =C66+VLOOKUP(A66,Windows!$A$24:$C$30,2,FALSE) | I66: =C66+VLOOKUP(A66,Windows!$A$24:$C$30,3,FALSE) | J66: =I66-Windows!$B$2 | K66: =IF(Windows!$B$2>I66,"expired",IF(Windows!$B$2<H66,"not_yet_eligible",IF(J66<=Windows!$B$9,"expiring","open"))) | L66: =VLOOKUP(A66,Windows!$A$15:$B$21,2,FALSE) | M66: =IF(G66="","",G66*L66) | N66: landed cost on file
A67: refund_no_return | B67: TH-TRICOR-23 | C67: 46199 | D67: 1 | E67: 111-4011243-8461978 | F67: 12.6 | G67: =IF(F67="","",D67*F67) | H67: =C67+VLOOKUP(A67,Windows!$A$24:$C$30,2,FALSE) | I67: =C67+VLOOKUP(A67,Windows!$A$24:$C$30,3,FALSE) | J67: =I67-Windows!$B$2 | K67: =IF(Windows!$B$2>I67,"expired",IF(Windows!$B$2<H67,"not_yet_eligible",IF(J67<=Windows!$B$9,"expiring","open"))) | L67: =VLOOKUP(A67,Windows!$A$15:$B$21,2,FALSE) | M67: =IF(G67="","",G67*L67) | N67: refunded amount per unit — Amazon reimburses at its determined value, so this is the ceiling
A68: refund_no_return | B68: TH-TRICOR-23 | C68: 46166 | D68: 1 | E68: 111-4011334-2057147 | F68: 12.6 | G68: =IF(F68="","",D68*F68) | H68: =C68+VLOOKUP(A68,Windows!$A$24:$C$30,2,FALSE) | I68: =C68+VLOOKUP(A68,Windows!$A$24:$C$30,3,FALSE) | J68: =I68-Windows!$B$2 | K68: =IF(Windows!$B$2>I68,"expired",IF(Windows!$B$2<H68,"not_yet_eligible",IF(J68<=Windows!$B$9,"expiring","open"))) | L68: =VLOOKUP(A68,Windows!$A$15:$B$21,2,FALSE) | M68: =IF(G68="","",G68*L68) | N68: refunded amount per unit — Amazon reimburses at its determined value, so this is the ceiling
A69: damaged_return | B69: TH-KNISHA-11 | C69: 46254 | D69: 1 | E69: 111-4005459-9197180 | F69: =IFERROR(VLOOKUP(B69,COGS!$A$2:$G$25,7,FALSE),"") | G69: =IF(F69="","",D69*F69) | H69: =C69+VLOOKUP(A69,Windows!$A$24:$C$30,2,FALSE) | I69: =C69+VLOOKUP(A69,Windows!$A$24:$C$30,3,FALSE) | J69: =I69-Windows!$B$2 | K69: =IF(Windows!$B$2>I69,"expired",IF(Windows!$B$2<H69,"not_yet_eligible",IF(J69<=Windows!$B$9,"expiring","open"))) | L69: =VLOOKUP(A69,Windows!$A$15:$B$21,2,FALSE) | M69: =IF(G69="","",G69*L69) | N69: landed cost on file
A70: damaged_return | B70: TH-COFCAN-19 | C70: 46263 | D70: 1 | E70: 111-4009157-6843329 | F70: =IFERROR(VLOOKUP(B70,COGS!$A$2:$G$25,7,FALSE),"") | G70: =IF(F70="","",D70*F70) | H70: =C70+VLOOKUP(A70,Windows!$A$24:$C$30,2,FALSE) | I70: =C70+VLOOKUP(A70,Windows!$A$24:$C$30,3,FALSE) | J70: =I70-Windows!$B$2 | K70: =IF(Windows!$B$2>I70,"expired",IF(Windows!$B$2<H70,"not_yet_eligible",IF(J70<=Windows!$B$9,"expiring","open"))) | L70: =VLOOKUP(A70,Windows!$A$15:$B$21,2,FALSE) | M70: =IF(G70="","",G70*L70) | N70: landed cost on file
A71: damaged_return | B71: TH-MEACUP-14 | C71: 46233 | D71: 1 | E71: 111-4006803-1795361 | F71: =IFERROR(VLOOKUP(B71,COGS!$A$2:$G$25,7,FALSE),"") | G71: =IF(F71="","",D71*F71) | H71: =C71+VLOOKUP(A71,Windows!$A$24:$C$30,2,FALSE) | I71: =C71+VLOOKUP(A71,Windows!$A$24:$C$30,3,FALSE) | J71: =I71-Windows!$B$2 | K71: =IF(Windows!$B$2>I71,"expired",IF(Windows!$B$2<H71,"not_yet_eligible",IF(J71<=Windows!$B$9,"expiring","open"))) | L71: =VLOOKUP(A71,Windows!$A$15:$B$21,2,FALSE) | M71: =IF(G71="","",G71*L71) | N71: landed cost on file
A72: damaged_return | B72: TH-MEACUP-14 | C72: 46253 | D72: 1 | E72: 111-4007087-1150864 | F72: =IFERROR(VLOOKUP(B72,COGS!$A$2:$G$25,7,FALSE),"") | G72: =IF(F72="","",D72*F72) | H72: =C72+VLOOKUP(A72,Windows!$A$24:$C$30,2,FALSE) | I72: =C72+VLOOKUP(A72,Windows!$A$24:$C$30,3,FALSE) | J72: =I72-Windows!$B$2 | K72: =IF(Windows!$B$2>I72,"expired",IF(Windows!$B$2<H72,"not_yet_eligible",IF(J72<=Windows!$B$9,"expiring","open"))) | L72: =VLOOKUP(A72,Windows!$A$15:$B$21,2,FALSE) | M72: =IF(G72="","",G72*L72) | N72: landed cost on file
A73: damaged_return | B73: TH-OVEMIT-22 | C73: 46258 | D73: 1 | E73: 111-4010633-4509044 | F73: =IFERROR(VLOOKUP(B73,COGS!$A$2:$G$25,7,FALSE),"") | G73: =IF(F73="","",D73*F73) | H73: =C73+VLOOKUP(A73,Windows!$A$24:$C$30,2,FALSE) | I73: =C73+VLOOKUP(A73,Windows!$A$24:$C$30,3,FALSE) | J73: =I73-Windows!$B$2 | K73: =IF(Windows!$B$2>I73,"expired",IF(Windows!$B$2<H73,"not_yet_eligible",IF(J73<=Windows!$B$9,"expiring","open"))) | L73: =VLOOKUP(A73,Windows!$A$15:$B$21,2,FALSE) | M73: =IF(G73="","",G73*L73) | N73: landed cost on file
A74: warehouse_damaged | B74: TH-ENADUT-03 | C74: 46254 | D74: 10 | F74: =IFERROR(VLOOKUP(B74,COGS!$A$2:$G$25,7,FALSE),"") | G74: =IF(F74="","",D74*F74) | H74: =C74+VLOOKUP(A74,Windows!$A$24:$C$30,2,FALSE) | I74: =C74+VLOOKUP(A74,Windows!$A$24:$C$30,3,FALSE) | J74: =I74-Windows!$B$2 | K74: =IF(Windows!$B$2>I74,"expired",IF(Windows!$B$2<H74,"not_yet_eligible",IF(J74<=Windows!$B$9,"expiring","open"))) | L74: =VLOOKUP(A74,Windows!$A$15:$B$21,2,FALSE) | M74: =IF(G74="","",G74*L74) | N74: landed cost on file
A75: warehouse_damaged | B75: TH-CASIRO-02 | C75: 46250 | D75: 11 | F75: =IFERROR(VLOOKUP(B75,COGS!$A$2:$G$25,7,FALSE),"") | G75: =IF(F75="","",D75*F75) | H75: =C75+VLOOKUP(A75,Windows!$A$24:$C$30,2,FALSE) | I75: =C75+VLOOKUP(A75,Windows!$A$24:$C$30,3,FALSE) | J75: =I75-Windows!$B$2 | K75: =IF(Windows!$B$2>I75,"expired",IF(Windows!$B$2<H75,"not_yet_eligible",IF(J75<=Windows!$B$9,"expiring","open"))) | L75: =VLOOKUP(A75,Windows!$A$15:$B$21,2,FALSE) | M75: =IF(G75="","",G75*L75) | N75: landed cost on file
A76: warehouse_damaged | B76: TH-CHEKNI-08 | C76: 46245 | D76: 7 | F76: =IFERROR(VLOOKUP(B76,COGS!$A$2:$G$25,7,FALSE),"") | G76: =IF(F76="","",D76*F76) | H76: =C76+VLOOKUP(A76,Windows!$A$24:$C$30,2,FALSE) | I76: =C76+VLOOKUP(A76,Windows!$A$24:$C$30,3,FALSE) | J76: =I76-Windows!$B$2 | K76: =IF(Windows!$B$2>I76,"expired",IF(Windows!$B$2<H76,"not_yet_eligible",IF(J76<=Windows!$B$9,"expiring","open"))) | L76: =VLOOKUP(A76,Windows!$A$15:$B$21,2,FALSE) | M76: =IF(G76="","",G76*L76) | N76: landed cost on file
A77: warehouse_damaged | B77: TH-PEPMIL-16 | C77: 46254 | D77: 10 | F77: =IFERROR(VLOOKUP(B77,COGS!$A$2:$G$25,7,FALSE),"") | G77: =IF(F77="","",D77*F77) | H77: =C77+VLOOKUP(A77,Windows!$A$24:$C$30,2,FALSE) | I77: =C77+VLOOKUP(A77,Windows!$A$24:$C$30,3,FALSE) | J77: =I77-Windows!$B$2 | K77: =IF(Windows!$B$2>I77,"expired",IF(Windows!$B$2<H77,"not_yet_eligible",IF(J77<=Windows!$B$9,"expiring","open"))) | L77: =VLOOKUP(A77,Windows!$A$15:$B$21,2,FALSE) | M77: =IF(G77="","",G77*L77) | N77: landed cost on file
A78: warehouse_damaged | B78: TH-WALSER-07 | C78: 46249 | D78: 7 | F78: =IFERROR(VLOOKUP(B78,COGS!$A$2:$G$25,7,FALSE),"") | G78: =IF(F78="","",D78*F78) | H78: =C78+VLOOKUP(A78,Windows!$A$24:$C$30,2,FALSE) | I78: =C78+VLOOKUP(A78,Windows!$A$24:$C$30,3,FALSE) | J78: =I78-Windows!$B$2 | K78: =IF(Windows!$B$2>I78,"expired",IF(Windows!$B$2<H78,"not_yet_eligible",IF(J78<=Windows!$B$9,"expiring","open"))) | L78: =VLOOKUP(A78,Windows!$A$15:$B$21,2,FALSE) | M78: =IF(G78="","",G78*L78) | N78: landed cost on file
A79: warehouse_damaged | B79: TH-BAMCUT-05 | C79: 46247 | D79: 11 | F79: =IFERROR(VLOOKUP(B79,COGS!$A$2:$G$25,7,FALSE),"") | G79: =IF(F79="","",D79*F79) | H79: =C79+VLOOKUP(A79,Windows!$A$24:$C$30,2,FALSE) | I79: =C79+VLOOKUP(A79,Windows!$A$24:$C$30,3,FALSE) | J79: =I79-Windows!$B$2 | K79: =IF(Windows!$B$2>I79,"expired",IF(Windows!$B$2<H79,"not_yet_eligible",IF(J79<=Windows!$B$9,"expiring","open"))) | L79: =VLOOKUP(A79,Windows!$A$15:$B$21,2,FALSE) | M79: =IF(G79="","",G79*L79) | N79: landed cost on file
A80: warehouse_damaged | B80: TH-POUOVE-18 | C80: 46249 | D80: 4 | F80: =IFERROR(VLOOKUP(B80,COGS!$A$2:$G$25,7,FALSE),"") | G80: =IF(F80="","",D80*F80) | H80: =C80+VLOOKUP(A80,Windows!$A$24:$C$30,2,FALSE) | I80: =C80+VLOOKUP(A80,Windows!$A$24:$C$30,3,FALSE) | J80: =I80-Windows!$B$2 | K80: =IF(Windows!$B$2>I80,"expired",IF(Windows!$B$2<H80,"not_yet_eligible",IF(J80<=Windows!$B$9,"expiring","open"))) | L80: =VLOOKUP(A80,Windows!$A$15:$B$21,2,FALSE) | M80: =IF(G80="","",G80*L80) | N80: landed cost on file
A81: warehouse_damaged | B81: TH-APRWAX-21 | C81: 46243 | D81: 5 | F81: =IFERROR(VLOOKUP(B81,COGS!$A$2:$G$25,7,FALSE),"") | G81: =IF(F81="","",D81*F81) | H81: =C81+VLOOKUP(A81,Windows!$A$24:$C$30,2,FALSE) | I81: =C81+VLOOKUP(A81,Windows!$A$24:$C$30,3,FALSE) | J81: =I81-Windows!$B$2 | K81: =IF(Windows!$B$2>I81,"expired",IF(Windows!$B$2<H81,"not_yet_eligible",IF(J81<=Windows!$B$9,"expiring","open"))) | L81: =VLOOKUP(A81,Windows!$A$15:$B$21,2,FALSE) | M81: =IF(G81="","",G81*L81) | N81: landed cost on file
A82: warehouse_damaged | B82: TH-STAMIX-12 | C82: 46241 | D82: 4 | F82: =IFERROR(VLOOKUP(B82,COGS!$A$2:$G$25,7,FALSE),"") | G82: =IF(F82="","",D82*F82) | H82: =C82+VLOOKUP(A82,Windows!$A$24:$C$30,2,FALSE) | I82: =C82+VLOOKUP(A82,Windows!$A$24:$C$30,3,FALSE) | J82: =I82-Windows!$B$2 | K82: =IF(Windows!$B$2>I82,"expired",IF(Windows!$B$2<H82,"not_yet_eligible",IF(J82<=Windows!$B$9,"expiring","open"))) | L82: =VLOOKUP(A82,Windows!$A$15:$B$21,2,FALSE) | M82: =IF(G82="","",G82*L82) | N82: landed cost on file
A83: warehouse_damaged | B83: TH-SALCEL-15 | C83: 46252 | D83: 10 | F83: =IFERROR(VLOOKUP(B83,COGS!$A$2:$G$25,7,FALSE),"") | G83: =IF(F83="","",D83*F83) | H83: =C83+VLOOKUP(A83,Windows!$A$24:$C$30,2,FALSE) | I83: =C83+VLOOKUP(A83,Windows!$A$24:$C$30,3,FALSE) | J83: =I83-Windows!$B$2 | K83: =IF(Windows!$B$2>I83,"expired",IF(Windows!$B$2<H83,"not_yet_eligible",IF(J83<=Windows!$B$9,"expiring","open"))) | L83: =VLOOKUP(A83,Windows!$A$15:$B$21,2,FALSE) | M83: =IF(G83="","",G83*L83) | N83: landed cost on file
A84: warehouse_damaged | B84: TH-KNISHA-11 | C84: 46248 | D84: 6 | F84: =IFERROR(VLOOKUP(B84,COGS!$A$2:$G$25,7,FALSE),"") | G84: =IF(F84="","",D84*F84) | H84: =C84+VLOOKUP(A84,Windows!$A$24:$C$30,2,FALSE) | I84: =C84+VLOOKUP(A84,Windows!$A$24:$C$30,3,FALSE) | J84: =I84-Windows!$B$2 | K84: =IF(Windows!$B$2>I84,"expired",IF(Windows!$B$2<H84,"not_yet_eligible",IF(J84<=Windows!$B$9,"expiring","open"))) | L84: =VLOOKUP(A84,Windows!$A$15:$B$21,2,FALSE) | M84: =IF(G84="","",G84*L84) | N84: landed cost on file
A85: warehouse_damaged | B85: TH-OVEMIT-22 | C85: 46240 | D85: 8 | F85: =IFERROR(VLOOKUP(B85,COGS!$A$2:$G$25,7,FALSE),"") | G85: =IF(F85="","",D85*F85) | H85: =C85+VLOOKUP(A85,Windows!$A$24:$C$30,2,FALSE) | I85: =C85+VLOOKUP(A85,Windows!$A$24:$C$30,3,FALSE) | J85: =I85-Windows!$B$2 | K85: =IF(Windows!$B$2>I85,"expired",IF(Windows!$B$2<H85,"not_yet_eligible",IF(J85<=Windows!$B$9,"expiring","open"))) | L85: =VLOOKUP(A85,Windows!$A$15:$B$21,2,FALSE) | M85: =IF(G85="","",G85*L85) | N85: landed cost on file
... A89: warehouse_damaged | B89: TH-KITTOW-24 | C89: 46251 | D89: 4 | F89: =IFERROR(VLOOKUP(B89,COGS!$A$2:$G$25,7,FALSE),"") | G89: =IF(F89="","",D89*F89) | H89: =C89+VLOOKUP(A89,Windows!$A$24:$C$30,2,FALSE) | I89: =C89+VLOOKUP(A89,Windows!$A$24:$C$30,3,FALSE) | J89: =I89-Windows!$B$2 | K89: =IF(Windows!$B$2>I89,"expired",IF(Windows!$B$2<H89,"not_yet_eligible",IF(J89<=Windows!$B$9,"expiring","open"))) | L89: =VLOOKUP(A89,Windows!$A$15:$B$21,2,FALSE) | M89: =IF(G89="","",G89*L89) | N89: landed cost on file
A90: refund_no_return | B90: TH-BAMCUT-05 | C90: 46210 | D90: 1 | E90: 111-4002401-6618607 | F90: 27.15 | G90: =IF(F90="","",D90*F90) | H90: =C90+VLOOKUP(A90,Windows!$A$24:$C$30,2,FALSE) | I90: =C90+VLOOKUP(A90,Windows!$A$24:$C$30,3,FALSE) | J90: =I90-Windows!$B$2 | K90: =IF(Windows!$B$2>I90,"expired",IF(Windows!$B$2<H90,"not_yet_eligible",IF(J90<=Windows!$B$9,"expiring","open"))) | L90: =VLOOKUP(A90,Windows!$A$15:$B$21,2,FALSE) | M90: =IF(G90="","",G90*L90) | N90: refunded amount per unit — Amazon reimburses at its determined value, so this is the ceiling
A91: warehouse_damaged | B91: TH-BAMCUT-06 | C91: 46239 | D91: 4 | F91: =IFERROR(VLOOKUP(B91,COGS!$A$2:$G$25,7,FALSE),"") | G91: =IF(F91="","",D91*F91) | H91: =C91+VLOOKUP(A91,Windows!$A$24:$C$30,2,FALSE) | I91: =C91+VLOOKUP(A91,Windows!$A$24:$C$30,3,FALSE) | J91: =I91-Windows!$B$2 | K91: =IF(Windows!$B$2>I91,"expired",IF(Windows!$B$2<H91,"not_yet_eligible",IF(J91<=Windows!$B$9,"expiring","open"))) | L91: =VLOOKUP(A91,Windows!$A$15:$B$21,2,FALSE) | M91: =IF(G91="","",G91*L91) | N91: landed cost on file
A92: warehouse_damaged | B92: TH-MEACUP-14 | C92: 46247 | D92: 3 | F92: =IFERROR(VLOOKUP(B92,COGS!$A$2:$G$25,7,FALSE),"") | G92: =IF(F92="","",D92*F92) | H92: =C92+VLOOKUP(A92,Windows!$A$24:$C$30,2,FALSE) | I92: =C92+VLOOKUP(A92,Windows!$A$24:$C$30,3,FALSE) | J92: =I92-Windows!$B$2 | K92: =IF(Windows!$B$2>I92,"expired",IF(Windows!$B$2<H92,"not_yet_eligible",IF(J92<=Windows!$B$9,"expiring","open"))) | L92: =VLOOKUP(A92,Windows!$A$15:$B$21,2,FALSE) | M92: =IF(G92="","",G92*L92) | N92: landed cost on file
A93: refund_no_return | B93: TH-PARKNI-09 | C93: 46208 | D93: 1 | E93: 111-4004276-8446106 | F93: 18.42 | G93: =IF(F93="","",D93*F93) | H93: =C93+VLOOKUP(A93,Windows!$A$24:$C$30,2,FALSE) | I93: =C93+VLOOKUP(A93,Windows!$A$24:$C$30,3,FALSE) | J93: =I93-Windows!$B$2 | K93: =IF(Windows!$B$2>I93,"expired",IF(Windows!$B$2<H93,"not_yet_eligible",IF(J93<=Windows!$B$9,"expiring","open"))) | L93: =VLOOKUP(A93,Windows!$A$15:$B$21,2,FALSE) | M93: =IF(G93="","",G93*L93) | N93: refunded amount per unit — Amazon reimburses at its determined value, so this is the ceiling
A94: warehouse_damaged | B94: TH-SILSPA-13 | C94: 46255 | D94: 4 | F94: =IFERROR(VLOOKUP(B94,COGS!$A$2:$G$25,7,FALSE),"") | G94: =IF(F94="","",D94*F94) | H94: =C94+VLOOKUP(A94,Windows!$A$24:$C$30,2,FALSE) | I94: =C94+VLOOKUP(A94,Windows!$A$24:$C$30,3,FALSE) | J94: =I94-Windows!$B$2 | K94: =IF(Windows!$B$2>I94,"expired",IF(Windows!$B$2<H94,"not_yet_eligible",IF(J94<=Windows!$B$9,"expiring","open"))) | L94: =VLOOKUP(A94,Windows!$A$15:$B$21,2,FALSE) | M94: =IF(G94="","",G94*L94) | N94: landed cost on file
A95: warehouse_damaged | B95: TH-TRICOR-23 | C95: 46256 | D95: 3 | F95: =IFERROR(VLOOKUP(B95,COGS!$A$2:$G$25,7,FALSE),"") | G95: =IF(F95="","",D95*F95) | H95: =C95+VLOOKUP(A95,Windows!$A$24:$C$30,2,FALSE) | I95: =C95+VLOOKUP(A95,Windows!$A$24:$C$30,3,FALSE) | J95: =I95-Windows!$B$2 | K95: =IF(Windows!$B$2>I95,"expired",IF(Windows!$B$2<H95,"not_yet_eligible",IF(J95<=Windows!$B$9,"expiring","open"))) | L95: =VLOOKUP(A95,Windows!$A$15:$B$21,2,FALSE) | M95: =IF(G95="","",G95*L95) | N95: landed cost on file
A96: warehouse_lost | B96: TH-ENADUT-03 | C96: 46157 | D96: 4 | F96: =IFERROR(VLOOKUP(B96,COGS!$A$2:$G$25,7,FALSE),"") | G96: =IF(F96="","",D96*F96) | H96: =C96+VLOOKUP(A96,Windows!$A$24:$C$30,2,FALSE) | I96: =C96+VLOOKUP(A96,Windows!$A$24:$C$30,3,FALSE) | J96: =I96-Windows!$B$2 | K96: =IF(Windows!$B$2>I96,"expired",IF(Windows!$B$2<H96,"not_yet_eligible",IF(J96<=Windows!$B$9,"expiring","open"))) | L96: =VLOOKUP(A96,Windows!$A$15:$B$21,2,FALSE) | M96: =IF(G96="","",G96*L96) | N96: landed cost on file
A97: warehouse_lost | B97: TH-PEPMIL-16 | C97: 46177 | D97: 7 | F97: =IFERROR(VLOOKUP(B97,COGS!$A$2:$G$25,7,FALSE),"") | G97: =IF(F97="","",D97*F97) | H97: =C97+VLOOKUP(A97,Windows!$A$24:$C$30,2,FALSE) | I97: =C97+VLOOKUP(A97,Windows!$A$24:$C$30,3,FALSE) | J97: =I97-Windows!$B$2 | K97: =IF(Windows!$B$2>I97,"expired",IF(Windows!$B$2<H97,"not_yet_eligible",IF(J97<=Windows!$B$9,"expiring","open"))) | L97: =VLOOKUP(A97,Windows!$A$15:$B$21,2,FALSE) | M97: =IF(G97="","",G97*L97) | N97: landed cost on file
A98: warehouse_lost | B98: TH-CHEKNI-08 | C98: 46174 | D98: 4 | F98: =IFERROR(VLOOKUP(B98,COGS!$A$2:$G$25,7,FALSE),"") | G98: =IF(F98="","",D98*F98) | H98: =C98+VLOOKUP(A98,Windows!$A$24:$C$30,2,FALSE) | I98: =C98+VLOOKUP(A98,Windows!$A$24:$C$30,3,FALSE) | J98: =I98-Windows!$B$2 | K98: =IF(Windows!$B$2>I98,"expired",IF(Windows!$B$2<H98,"not_yet_eligible",IF(J98<=Windows!$B$9,"expiring","open"))) | L98: =VLOOKUP(A98,Windows!$A$15:$B$21,2,FALSE) | M98: =IF(G98="","",G98*L98) | N98: landed cost on file
A99: warehouse_lost | B99: TH-CARSTE-04 | C99: 46193 | D99: 4 | F99: =IFERROR(VLOOKUP(B99,COGS!$A$2:$G$25,7,FALSE),"") | G99: =IF(F99="","",D99*F99) | H99: =C99+VLOOKUP(A99,Windows!$A$24:$C$30,2,FALSE) | I99: =C99+VLOOKUP(A99,Windows!$A$24:$C$30,3,FALSE) | J99: =I99-Windows!$B$2 | K99: =IF(Windows!$B$2>I99,"expired",IF(Windows!$B$2<H99,"not_yet_eligible",IF(J99<=Windows!$B$9,"expiring","open"))) | L99: =VLOOKUP(A99,Windows!$A$15:$B$21,2,FALSE) | M99: =IF(G99="","",G99*L99) | N99: landed cost on file
A100: warehouse_lost | B100: TH-WALSER-07 | C100: 46182 | D100: 4 | F100: =IFERROR(VLOOKUP(B100,COGS!$A$2:$G$25,7,FALSE),"") | G100: =IF(F100="","",D100*F100) | H100: =C100+VLOOKUP(A100,Windows!$A$24:$C$30,2,FALSE) | I100: =C100+VLOOKUP(A100,Windows!$A$24:$C$30,3,FALSE) | J100: =I100-Windows!$B$2 | K100: =IF(Windows!$B$2>I100,"expired",IF(Windows!$B$2<H100,"not_yet_eligible",IF(J100<=Windows!$B$9,"expiring","open"))) | L100: =VLOOKUP(A100,Windows!$A$15:$B$21,2,FALSE) | M100: =IF(G100="","",G100*L100) | N100: landed cost on file
A101: warehouse_lost | B101: TH-MEACUP-14 | C101: 46172 | D101: 8 | F101: =IFERROR(VLOOKUP(B101,COGS!$A$2:$G$25,7,FALSE),"") | G101: =IF(F101="","",D101*F101) | H101: =C101+VLOOKUP(A101,Windows!$A$24:$C$30,2,FALSE) | I101: =C101+VLOOKUP(A101,Windows!$A$24:$C$30,3,FALSE) | J101: =I101-Windows!$B$2 | K101: =IF(Windows!$B$2>I101,"expired",IF(Windows!$B$2<H101,"not_yet_eligible",IF(J101<=Windows!$B$9,"expiring","open"))) | L101: =VLOOKUP(A101,Windows!$A$15:$B$21,2,FALSE) | M101: =IF(G101="","",G101*L101) | N101: landed cost on file
A102: warehouse_lost | B102: TH-BREKNI-10 | C102: 46169 | D102: 5 | F102: =IFERROR(VLOOKUP(B102,COGS!$A$2:$G$25,7,FALSE),"") | G102: =IF(F102="","",D102*F102) | H102: =C102+VLOOKUP(A102,Windows!$A$24:$C$30,2,FALSE) | I102: =C102+VLOOKUP(A102,Windows!$A$24:$C$30,3,FALSE) | J102: =I102-Windows!$B$2 | K102: =IF(Windows!$B$2>I102,"expired",IF(Windows!$B$2<H102,"not_yet_eligible",IF(J102<=Windows!$B$9,"expiring","open"))) | L102: =VLOOKUP(A102,Windows!$A$15:$B$21,2,FALSE) | M102: =IF(G102="","",G102*L102) | N102: landed cost on file
A103: warehouse_lost | B103: TH-BAMCUT-06 | C103: 46167 | D103: 7 | F103: =IFERROR(VLOOKUP(B103,COGS!$A$2:$G$25,7,FALSE),"") | G103: =IF(F103="","",D103*F103) | H103: =C103+VLOOKUP(A103,Windows!$A$24:$C$30,2,FALSE) | I103: =C103+VLOOKUP(A103,Windows!$A$24:$C$30,3,FALSE) | J103: =I103-Windows!$B$2 | K103: =IF(Windows!$B$2>I103,"expired",IF(Windows!$B$2<H103,"not_yet_eligible",IF(J103<=Windows!$B$9,"expiring","open"))) | L103: =VLOOKUP(A103,Windows!$A$15:$B$21,2,FALSE) | M103: =IF(G103="","",G103*L103) | N103: landed cost on file
A104: warehouse_lost | B104: TH-KITTOW-24 | C104: 46195 | D104: 6 | F104: =IFERROR(VLOOKUP(B104,COGS!$A$2:$G$25,7,FALSE),"") | G104: =IF(F104="","",D104*F104) | H104: =C104+VLOOKUP(A104,Windows!$A$24:$C$30,2,FALSE) | I104: =C104+VLOOKUP(A104,Windows!$A$24:$C$30,3,FALSE) | J104: =I104-Windows!$B$2 | K104: =IF(Windows!$B$2>I104,"expired",IF(Windows!$B$2<H104,"not_yet_eligible",IF(J104<=Windows!$B$9,"expiring","open"))) | L104: =VLOOKUP(A104,Windows!$A$15:$B$21,2,FALSE) | M104: =IF(G104="","",G104*L104) | N104: landed cost on file
A105: warehouse_lost | B105: TH-CASIRO-01 | C105: 46160 | D105: 3 | F105: =IFERROR(VLOOKUP(B105,COGS!$A$2:$G$25,7,FALSE),"") | G105: =IF(F105="","",D105*F105) | H105: =C105+VLOOKUP(A105,Windows!$A$24:$C$30,2,FALSE) | I105: =C105+VLOOKUP(A105,Windows!$A$24:$C$30,3,FALSE) | J105: =I105-Windows!$B$2 | K105: =IF(Windows!$B$2>I105,"expired",IF(Windows!$B$2<H105,"not_yet_eligible",IF(J105<=Windows!$B$9,"expiring","open"))) | L105: =VLOOKUP(A105,Windows!$A$15:$B$21,2,FALSE) | M105: =IF(G105="","",G105*L105) | N105: landed cost on file
... A111: warehouse_lost | B111: TH-BAMCUT-05 | C111: 46162 | D111: 2 | F111: =IFERROR(VLOOKUP(B111,COGS!$A$2:$G$25,7,FALSE),"") | G111: =IF(F111="","",D111*F111) | H111: =C111+VLOOKUP(A111,Windows!$A$24:$C$30,2,FALSE) | I111: =C111+VLOOKUP(A111,Windows!$A$24:$C$30,3,FALSE) | J111: =I111-Windows!$B$2 | K111: =IF(Windows!$B$2>I111,"expired",IF(Windows!$B$2<H111,"not_yet_eligible",IF(J111<=Windows!$B$9,"expiring","open"))) | L111: =VLOOKUP(A111,Windows!$A$15:$B$21,2,FALSE) | M111: =IF(G111="","",G111*L111) | N111: landed cost on file
A112: damaged_return | B112: TH-CASIRO-02 | C112: 46170 | D112: 1 | E112: 111-4001074-3177903 | F112: =IFERROR(VLOOKUP(B112,COGS!$A$2:$G$25,7,FALSE),"") | G112: =IF(F112="","",D112*F112) | H112: =C112+VLOOKUP(A112,Windows!$A$24:$C$30,2,FALSE) | I112: =C112+VLOOKUP(A112,Windows!$A$24:$C$30,3,FALSE) | J112: =I112-Windows!$B$2 | K112: =IF(Windows!$B$2>I112,"expired",IF(Windows!$B$2<H112,"not_yet_eligible",IF(J112<=Windows!$B$9,"expiring","open"))) | L112: =VLOOKUP(A112,Windows!$A$15:$B$21,2,FALSE) | M112: =IF(G112="","",G112*L112) | N112: landed cost on file
A113: damaged_return | B113: TH-CARSTE-04 | C113: 46189 | D113: 1 | E113: 111-4001923-2381660 | F113: =IFERROR(VLOOKUP(B113,COGS!$A$2:$G$25,7,FALSE),"") | G113: =IF(F113="","",D113*F113) | H113: =C113+VLOOKUP(A113,Windows!$A$24:$C$30,2,FALSE) | I113: =C113+VLOOKUP(A113,Windows!$A$24:$C$30,3,FALSE) | J113: =I113-Windows!$B$2 | K113: =IF(Windows!$B$2>I113,"expired",IF(Windows!$B$2<H113,"not_yet_eligible",IF(J113<=Windows!$B$9,"expiring","open"))) | L113: =VLOOKUP(A113,Windows!$A$15:$B$21,2,FALSE) | M113: =IF(G113="","",G113*L113) | N113: landed cost on file
A114: warehouse_lost | B114: TH-PARKNI-09 | C114: 46162 | D114: 2 | F114: =IFERROR(VLOOKUP(B114,COGS!$A$2:$G$25,7,FALSE),"") | G114: =IF(F114="","",D114*F114) | H114: =C114+VLOOKUP(A114,Windows!$A$24:$C$30,2,FALSE) | I114: =C114+VLOOKUP(A114,Windows!$A$24:$C$30,3,FALSE) | J114: =I114-Windows!$B$2 | K114: =IF(Windows!$B$2>I114,"expired",IF(Windows!$B$2<H114,"not_yet_eligible",IF(J114<=Windows!$B$9,"expiring","open"))) | L114: =VLOOKUP(A114,Windows!$A$15:$B$21,2,FALSE) | M114: =IF(G114="","",G114*L114) | N114: landed cost on file
A115: damaged_return | B115: TH-CASIRO-01 | C115: 46167 | D115: 1 | E115: 111-4000215-7071290 | F115: =IFERROR(VLOOKUP(B115,COGS!$A$2:$G$25,7,FALSE),"") | G115: =IF(F115="","",D115*F115) | H115: =C115+VLOOKUP(A115,Windows!$A$24:$C$30,2,FALSE) | I115: =C115+VLOOKUP(A115,Windows!$A$24:$C$30,3,FALSE) | J115: =I115-Windows!$B$2 | K115: =IF(Windows!$B$2>I115,"expired",IF(Windows!$B$2<H115,"not_yet_eligible",IF(J115<=Windows!$B$9,"expiring","open"))) | L115: =VLOOKUP(A115,Windows!$A$15:$B$21,2,FALSE) | M115: =IF(G115="","",G115*L115) | N115: landed cost on file
A116: damaged_return | B116: TH-CASIRO-01 | C116: 46173 | D116: 1 | E116: 111-4000484-5296207 | F116: =IFERROR(VLOOKUP(B116,COGS!$A$2:$G$25,7,FALSE),"") | G116: =IF(F116="","",D116*F116) | H116: =C116+VLOOKUP(A116,Windows!$A$24:$C$30,2,FALSE) | I116: =C116+VLOOKUP(A116,Windows!$A$24:$C$30,3,FALSE) | J116: =I116-Windows!$B$2 | K116: =IF(Windows!$B$2>I116,"expired",IF(Windows!$B$2<H116,"not_yet_eligible",IF(J116<=Windows!$B$9,"expiring","open"))) | L116: =VLOOKUP(A116,Windows!$A$15:$B$21,2,FALSE) | M116: =IF(G116="","",G116*L116) | N116: landed cost on file
A117: damaged_return | B117: TH-PEPMIL-16 | C117: 46182 | D117: 1 | E117: 111-4007751-8335136 | F117: =IFERROR(VLOOKUP(B117,COGS!$A$2:$G$25,7,FALSE),"") | G117: =IF(F117="","",D117*F117) | H117: =C117+VLOOKUP(A117,Windows!$A$24:$C$30,2,FALSE) | I117: =C117+VLOOKUP(A117,Windows!$A$24:$C$30,3,FALSE) | J117: =I117-Windows!$B$2 | K117: =IF(Windows!$B$2>I117,"expired",IF(Windows!$B$2<H117,"not_yet_eligible",IF(J117<=Windows!$B$9,"expiring","open"))) | L117: =VLOOKUP(A117,Windows!$A$15:$B$21,2,FALSE) | M117: =IF(G117="","",G117*L117) | N117: landed cost on file
...

Sheet Filing log
A1: Claim row | B1: SKU | C1: Case id | D1: Filed on | E1: Amazon's answer | F1: Paid in cash | G1: Replaced in inventory (units) | H1: Paid on | I1: Notes
